Workbook

Sheet Browse by Category
B1: Browse by Category - generated from 'Asset Index'; use the filter buttons on row 2
B2: id | C2: asset name | D2: category | E2: status | F2: section | G2: priority | H2: price | I2: in Mr Moonlight? | J2: up to date? | K2: purpose in Mr Moonlight | L2: description | M2: notes | N2: collection url | O2: asset store / source | P2: documentation | Q2: downloaded file | R2: publisher | S2: latest version (store) | T2: store updated
B3: AST-041 | C3: Blaze AI Engine | D3: AI & Behavior | E3: Owned | F3: Owned | H3: 40 | I3: Yes | J3: No | K3: MRM-34 Spotter AI and the shared enemy framework (MRM-27 onward). Verified live. | L3: Universal enemy/companion AI: patrol, chase, cover-shooting, hit states on NavMesh. | N3: Collection ↗ | O3: Asset Store ↗ | Q3: Blaze AI Engine v3.4.21 (20 May 2026) | R3: Pathiral | S3: 3.4.22 | T3: 2026-06-22
B4: AST-042 | C4: A* Pathfinding Project Pro | D4: AI & Behavior | E4: Owned | F4: Owned | H4: 140 | I4: No | J4: No | K4: Dropped in Round 2 in favour of Blaze AI (NavMesh). Keep for other projects. | L4: Fast, flexible pathfinding (grid, navmesh, recast) for large worlds. | N4: Collection ↗ | O4: Asset Store ↗ | P4: Docs ↗ | Q4: A Pathfinding Project Pro v5.4.6 | R4: Aron Granberg | S4: 5.4.7 | T4: 2026-08-29
B5: AST-169 | C5: Advanced Zombie AI | D5: AI & Behavior | E5: Owned | F5: Owned (not in project) | G5: Owned (was P2 · #69) | H5: 15 | I5: No | J5: No | K5: Would overlap with Blaze AI — reference only. | L5: Configurable zombie AI system. | M5: [Claude] Merged duplicate (was listed twice). | N5: Collection ↗ | O5: Asset Store ↗ | P5: Docs ↗ | Q5: Advanced Zombie AI v1.0.3 | R5: Finite Machine Studio | S5: 1.0.4 | T5: 2026-07-30
B6: AST-264 | C6: SensorToolkit 2 | D6: AI & Behavior | E6: Owned | F6: Owned (not in project) | G6: Owned (new · not on original list) | H6: 45 | I6: No | J6: Yes | K6: Not assigned yet. Candidate for enemy senses (vision / proximity) - overlaps Blaze AI's built-in detection, so evaluate before adopting. | L6: Sensor components (raycast, range, field-of-view, trigger) that detect and report nearby objects. | M6: [Claude] Added 2026-09-19 — acquired outside the original list; not installed in any project yet. | N6: Collection ↗ | O6: Asset Store ↗ | Q6: SensorToolkit 2 v2.5.19 | R6: Micosmo | S6: 2.5.19 | T6: 2026-09-12
B7: AST-265 | C7: Emerald AI 2026 | D7: AI & Behavior | E7: Owned | F7: Owned (not in project) | G7: Owned (new · not on original list) | H7: 60 | I7: No | J7: Yes | K7: Not assigned yet. Alternative enemy AI framework - Mr. Moonlight's enemies run on Blaze AI, so reference/comparison only unless that changes. | L7: Universal AI framework, rewritten: modular components, easy editors, many built-in features. | M7: [Claude] Added 2026-09-19 — acquired outside the original list; not installed in any project yet. | N7: Collection ↗ | O7: Asset Store ↗ | Q7: Emerald AI 2026 v1.3.4 | R7: Black Horizon Studios | S7: 1.3.4 | T7: 2026-09-14
B8: AST-300 | C8: Mobile Traffic System v3 | D8: AI & Behavior | E8: Owned | F8: Owned (not in project) | G8: Owned (new · not on original list) | H8: 129 | I8: No | J8: No | K8: Not assigned yet. Other projects (driving). | L8: Traffic system for vehicle AI and city traffic (store page has no description; summary from title and tags). | M8: [Claude] Added 2026-10-08 — acquired outside the original list. File v3.6.1 is behind the store (3.6.5). Not installed anywhere. | N8: Collection ↗ | O8: Asset Store ↗ | Q8: Mobile Traffic System v3 v3.6.1 | R8: Gley | S8: 3.6.5 | T8: 2026-09-29
B9: AST-101 | C9: Blaze AI Engine - Hearing | D9: AI & Behavior | E9: Wishlist | F9: Wishlist P1 | G9: P1 · #1 | H9: 7.99 | I9: No | J9: — | K9: Enemies react to gunshots and footsteps — direct upgrade to the Spotter/enemy framework. | L9: Blaze AI module: agents hear sounds on chosen layers. | M9: Can be used for hearing detection on the Blaze engine. | O9: Asset Store ↗ | R9: Pathiral | S9: 1.0.1 | T9: 2025-07-04
B10: AST-102 | C10: Blaze AI Engine - Predator | D10: AI & Behavior | E10: Wishlist | F10: Wishlist P1 | G10: P1 · #2 | H10: 15 | I10: No | J10: — | K10: Stalking behaviour for the Wendigo, the wolf and feral enemies. | L10: Blaze AI module: predator behaviour that stalks and hunts prey. | M10: Can be used to extend the Blaze behaviors for the enemies | O10: Asset Store ↗ | R10: Pathiral | S10: 1.3.0 | T10: 2025-05-10
B11: AST-013 | C11: Retarget Pro V5 | D11: Animation & Rigging Tools | E11: Owned | F11: Owned | H11: 59.99 | I11: No | J11: Yes | K11: Deliberately Playground-only: bakes clips for the Wendigo, wolf and Tracey's body (MRM-75 / MRM-36). Only the baked clips migrate, the tool never does. | L11: Animation retargeting between any rigs (Humanoid or not) with bake-to-clip output (KINEMATION). | N11: Collection ↗ | O11: Asset Store ↗ | P11: Docs ↗ | Q11: Retarget Pro V5 v5.2.1 | R11: KINEMATION | S11: 5.2.1 | T11: 2026-08-26
B12: AST-082 | C12: DOTween Pro | D12: Animation & Rigging Tools | E12: Owned | F12: Owned (added later) | H12: 15 | I12: Yes | J12: Unknown | K12: Project standard for smooth transitions (menu title reveal, UI fades). | L12: Tweening engine: move, fade, shake, paths and sequences, with visual editors. | M12: [Claude] Added — found in the project / project docs, was not on the list. | O12: Asset Store ↗ | P12: Docs ↗ | Q12: Installed — version not recorded | R12: Demigiant | S12: 1.0.430 | T12: 2026-06-23
B13: AST-103 | C13: Feel | D13: Animation & Rigging Tools | E13: Owned | F13: Owned (not in project) | G13: Owned (was P1 · #3) | H13: 50 | I13: No | J13: No | K13: Recoil, hit feedback, fear shakes and UI juice across many systems. | L13: Game-feel toolkit: screen shake, hit-stop, flashes, bounces, 150+ feedbacks. | M13: Very nice effects that bring life into animations and projects and whatever | N13: Collection ↗ | O13: Asset Store ↗ | P13: Docs ↗ | Q13: Feel v6.0 | R13: More Mountains | S13: 6.1 | T13: 2026-08-31
B14: AST-120 | C14: Final IK | D14: Animation & Rigging Tools | E14: Owned | F14: Owned (not in project) | G14: Owned (was P1 · #20) | H14: 90 | I14: No | J14: Yes | K14: Enemy aiming/look-at, foot grounding on sloped terrain, and Tracey's look-down body. | L14: Complete inverse-kinematics suite: aim, look-at, full-body biped, grounding. | M14: Could be useful for improving animations | N14: Collection ↗ | O14: Asset Store ↗ | Q14: Final IK v2.5 (11 Apr 2026) | R14: RootMotion | S14: 2.5 | T14: 2026-04-10
B15: AST-156 | C15: Mesh Transformation | D15: Animation & Rigging Tools | E15: Owned | F15: Owned (not in project) | G15: Owned (was P2 · #56) | H15: 14.45 | I15: No | J15: Yes | K15: The werewolf transformation. | L15: Mesh-to-mesh transformation animations (werewolf, mutant, healing). | M15: Could be useful for transformation. For example the werewolf enemy | N15: Collection ↗ | O15: Asset Store ↗ | Q15: Mesh Transformation v1.9 | R15: Andrey Graphics | S15: 1.9 | T15: 2020-09-02
B16: AST-172 | C16: Character Animation System | D16: Animation & Rigging Tools | E16: Owned | F16: Owned (not in project) | G16: Owned (was P3 · #72) | H16: 79.99 | I16: No | J16: No | K16: Later: procedural polish for Tracey's body. Mostly for future projects. | L16: Modular procedural animation layer: blending, IK, additive layers (KINEMATION). | N16: Collection ↗ | O16: Asset Store ↗ | P16: Docs ↗ | Q16: Character Animation System v2.1.2 | R16: KINEMATION | S16: 2.4.1 | T16: 2026-08-17
B17: AST-183 | C17: BoneToPix - 3D & Bone Animation To Pixel-Art Converter | D17: Animation & Rigging Tools | E17: Owned | F17: Owned (not in project) | G17: Owned (was P3 · #83) | H17: 24.99 | I17: No | J17: No | K17: Other projects (2D pixel art). | L17: Converts 3D models/animations into pixel-art sprites with lighting. | N17: Collection ↗ | O17: Asset Store ↗ | Q17: BoneToPix - 3D Bone Animation To Pixel-Art Converter v2.9.1 | R17: GeorgeBGreen | S17: 2.9.2 | T17: 2025-08-07
B18: AST-197 | C18: Animation to Sprite Sheet – Export animations into 2D sprite sheets easily | D18: Animation & Rigging Tools | E18: Owned | F18: Owned (not in project) | G18: Owned (was P3 · #97) | H18: 15 | I18: No | J18: Yes | K18: Other projects (2D). | L18: Exports 3D animations to 2D sprite sheets. | N18: Collection ↗ | O18: Asset Store ↗ | Q18: Animation to Sprite Sheet - Export animations into 2D sprite sheets easily v1.0 | R18: Zuppy | S18: 1.0 | T18: 2025-10-28
B19: AST-290 | C19: Tail Animator | D19: Animation & Rigging Tools | E19: Owned | F19: Owned (not in project) | G19: Owned (new · not on original list) | H19: 25.99 | I19: No | J19: Yes | K19: Not assigned yet. Procedural secondary motion (tails, hair, cloth-like parts) on creatures. | L19: Procedural tail / tentacle / secondary-motion animation tool. | M19: [Claude] Added 2026-10-05 — acquired outside the original list. | N19: Collection ↗ | O19: Asset Store ↗ | Q19: Tail Animator v2.5.3 (21 Sep 2026) | R19: FImpossible Creations | S19: 2.5.3 | T19: 2026-09-21
B20: AST-291 | C20: Legs Animator | D20: Animation & Rigging Tools | E20: Owned | F20: Owned (not in project) | G20: Owned (new · not on original list) | H20: 43.99 | I20: No | J20: Yes | K20: Not assigned yet. Procedural leg placement on uneven ground for creatures/enemies. | L20: Procedural leg placement and walking animation for humanoids and animals (spiders, insects). | M20: [Claude] Added 2026-10-05 — acquired outside the original list. | N20: Collection ↗ | O20: Asset Store ↗ | Q20: Legs Animator v1.0.4.6 (21 Sep 2026) | R20: FImpossible Creations | S20: 1.0.4.6 | T20: 2026-09-21
B21: AST-299 | C21: Animation Designer | D21: Animation & Rigging Tools | E21: Owned | F21: Owned (not in project) | G21: Owned (new · not on original list) | H21: 59.99 | I21: No | J21: Yes | K21: Not assigned yet. Animation tooling candidate. | L21: Animation authoring toolkit for procedural and humanoid animation, with IK support (store page has no description; summary from title and tags). | M21: [Claude] Added 2026-10-08 — acquired outside the original list. Not installed anywhere. | N21: Collection ↗ | O21: Asset Store ↗ | Q21: Animation Designer v1.3.1 (21 Sep 2026) | R21: FImpossible Creations | S21: 1.3.1 | T21: 2026-09-21
B22: AST-306 | C22: Jiggling | D22: Animation & Rigging Tools | E22: Owned | F22: Owned (not in project) | G22: Owned (new · not on original list) | H22: 4.99 | I22: No | J22: Yes | K22: Not assigned yet. Carlos's idea (2026-10-11): shake and wobble for the earthquake event. | L22: Jiggle animation by rotation and scaling only, two-click setup: hit impulses, scale pulses, source included. | M22: [Claude] Added 2026-10-11 — acquired outside the original list. | N22: Collection ↗ | O22: Asset Store ↗ | Q22: Jiggling v1.1.5 | R22: FImpossible Creations | S22: 1.1.5 | T22: 2026-10-07
B23: AST-311 | C23: AnimFuse - Animation Blending, Pose Editing and Baking | D23: Animation & Rigging Tools | E23: Owned | F23: Owned (not in project) | G23: Owned (new · not on original list) | H23: 19.99 | I23: No | J23: No | K23: Not assigned yet. Animation tooling for later or other projects. | L23: Animation blending, pose editing and baking, including upper-body and aiming setups for humanoids. | M23: [Claude] Added 2026-10-27 — acquired outside the original list. | N23: Collection ↗ | O23: Asset Store ↗ | Q23: AnimFuse Animation Blending Pose Editing and Baking v1.0 | R23: Finite Machine Studio | S23: 1.0.4 | T23: 2026-10-22
B24: AST-313 | C24: Realistic Eye Movements | D24: Animation & Rigging Tools | E24: Owned | F24: Owned (not in project) | G24: Owned (new · not on original list) | H24: 25 | I24: No | J24: Yes | K24: Not assigned yet. Eyes for enemies and characters; later or other projects. | L24: Realistic eye movement, gaze and blinking for characters. | M24: [Claude] Added 2026-10-27 — acquired outside the original list. | N24: Collection ↗ | O24: Asset Store ↗ | Q24: Realistic Eye Movements v2.1.14 | R24: Tore Knabe | S24: 2.1.14 | T24: 2026-03-16
B25: AST-019 | C25: Cult Animations | D25: Animation — Clips & Mocap | E25: Owned | F25: Owned | H25: 8 | I25: No | J25: Yes | K25: Adopted for MRM-59 cult staging scenes. | L25: 25 motion-captured cult / ritual animations. | N25: Collection ↗ | O25: Asset Store ↗ | Q25: Cult Animations v1.0 | R25: Gem Gaming Animations | S25: 1.0 | T25: 2024-05-31
B26: AST-022 | C26: ANIMSET: 2 HANDED MELEE WEAPON | D26: Animation — Clips & Mocap | E26: Owned | F26: Owned | H26: 19.99 | I26: No | J26: No | K26: Adopted for MRM-23 melee. Also included inside Ultimate Animation Collection. | L26: Mocap animation set for two-handed melee weapons. | N26: Collection ↗ | O26: Asset Store ↗ | Q26: ANIMSET 2 HANDED MELEE WEAPON v1.5 | R26: PROTOFACTOR, INC | S26: 1.642 | T26: 2026-07-06
B27: AST-026 | C27: Knife_MocapAnimPack_1.1 | D27: Animation — Clips & Mocap | E27: Owned | F27: Owned | H27: 45 | I27: No | J27: Yes | K27: Adopted for MRM-35 knife-wielding enemy. | L27: Mocap knife combat animation pack. | N27: Collection ↗ | O27: Asset Store ↗ | Q27: Knife_MocapAnimPack v1.1 (21 Aug 2026) | R27: RIB Studio | S27: 1.1 | T27: 2026-08-24
B28: AST-044 | C28: ULTIMATE ANIMATION COLLECTION | D28: Animation — Clips & Mocap | E28: Owned | F28: Owned | H28: 259.99 | I28: Yes | J28: Yes | K28: Installed — enemy locomotion/combat clips (MRM-31 / 29 / 35 / 37). ⚠ Import selectively. | L28: Huge human mocap library for Mecanim Humanoid (3,000+ clips). | N28: Collection ↗ | O28: Asset Store ↗ | Q28: ULTIMATE ANIMATION COLLECTION v1.65 | R28: PROTOFACTOR, INC | S28: 1.65 | T28: 2026-08-16
B29: AST-061 | C29: Human Mega Animations Pack | D29: Animation — Clips & Mocap | E29: Owned | F29: Owned | H29: 130 | I29: No | J29: Yes | K29: Extra humanoid clips for NPCs and enemies. | L29: All of Kevin Iglesias' human animations in one pack. | M29: A lot of useful animations | N29: Collection ↗ | O29: Asset Store ↗ | Q29: Human Mega Animations Pack v2.0 (06 May 2026) | R29: Kevin Iglesias | S29: 2.0 | T29: 2026-05-06
B30: AST-069 | C30: Stealth Finishers - Knife and Hand | D30: Animation — Clips & Mocap | E30: Owned | F30: Owned | H30: 39.99 | I30: No | J30: Yes | K30: Melee enemy attacks and takedowns. | L30: Knife/hand stealth finishers, cover movement and body carry/drag. | M30: Contains some animations that can be used for melee enemies. | N30: Collection ↗ | O30: Asset Store ↗ | Q30: Stealth Finishers - Knife and Hand v1.0 | R30: RamsterZ | S30: 1.0 | T30: 2022-07-04
B31: AST-121 | C31: Zombie Animations Set | D31: Animation — Clips & Mocap | E31: Owned | F31: Owned (not in project) | G31: Owned (was P1 · #21) | H31: 24.99 | I31: No | J31: No | K31: Zombie/feral enemies. | L31: Zombie animations: paired grabs, crawls, hit reactions, deaths. | M31: Can be useful for the zombies | N31: Collection ↗ | O31: Asset Store ↗ | Q31: Zombie Animations Set v1.0 | R31: RamsterZ | S31: 1.3.0 | T31: 2026-07-19
B32: AST-122 | C32: Ghost Creature Anims | D32: Animation — Clips & Mocap | E32: Owned | F32: Owned (not in project) | G32: Owned (was P1 · #22) | H32: 29.99 | I32: No | J32: Yes | K32: Enemy animations. | L32: 89 ghost and horror-victim animations with paired attacks. | M32: Useful animations for the enemies | N32: Collection ↗ | O32: Asset Store ↗ | Q32: Ghost Creature Anims v1.2 | R32: RamsterZ | S32: 1.2 | T32: 2022-07-04
B33: AST-123 | C33: Witch Hag Animations | D33: Animation — Clips & Mocap | E33: Owned | F33: Owned (not in project) | G33: Owned (was P1 · #23) | H33: 29.99 | I33: No | J33: Yes | K33: Enemy animations. | L33: Stooped witch/hag horror animations. | M33: Have useful animations for the enemies. | N33: Collection ↗ | O33: Asset Store ↗ | Q33: Witch Hag Animations v1.0 | R33: RamsterZ | S33: 1.0 | T33: 2023-09-27
B34: AST-124 | C34: Killer Doll Animations | D34: Animation — Clips & Mocap | E34: Owned | F34: Owned (not in project) | G34: Owned (was P1 · #24) | H34: 24.99 | I34: No | J34: Yes | K34: Enemy animations. | L34: Twitchy, unnatural doll/monster animations (+ bonus model). | M34: Useful animations for the enemies | N34: Collection ↗ | O34: Asset Store ↗ | Q34: Killer Doll Animations v1.0.1 | R34: RamsterZ | S34: 1.0.1 | T34: 2026-02-18
B35: AST-132 | C35: Dialogue Anims | D35: Animation — Clips & Mocap | E35: Owned | F35: Owned (not in project) | G35: Owned (was P1 · #32) | H35: 15 | I35: No | J35: Yes | K35: The Legion mode merchant. | L35: 104 dialogue/talking animations in many styles. | M35: Could be useful for the merchant. This is for the Legion mode on the store. | N35: Collection ↗ | O35: Asset Store ↗ | Q35: Dialogue Anims v1.0 | R35: RamsterZ | S35: 1.0 | T35: 2022-05-20
B36: AST-133 | C36: Classic Female Ghost | D36: Animation — Clips & Mocap | E36: Owned | F36: Owned (not in project) | G36: Owned (was P1 · #33) | H36: 29.99 | I36: No | J36: Yes | K36: Enemy animations. | L36: Ethereal female ghost/witch horror animations. | M36: Useful animations for the enemies Could have useful animations for the enemies [Claude] Merged duplicate (was listed twice). | N36: Collection ↗ | O36: Asset Store ↗ | Q36: Classic Female Ghost v1.0 | R36: RamsterZ | S36: 1.0 | T36: 2023-10-05
B37: AST-134 | C37: Demon Anims | D37: Animation — Clips & Mocap | E37: Owned | F37: Owned (not in project) | G37: Owned (was P1 · #34) | H37: 24.99 | I37: No | J37: Yes | K37: Enemy animations. | L37: Demon/ghost animations with jump scares and victim clips. | M37: Could have some useful animations | N37: Collection ↗ | O37: Asset Store ↗ | Q37: Demon Anims v1.0 | R37: RamsterZ | S37: 1.0 | T37: 2022-06-21
B38: AST-135 | C38: Asylum NPC Animations | D38: Animation — Clips & Mocap | E38: Owned | F38: Owned (not in project) | G38: Owned (was P1 · #35) | H38: 15.99 | I38: No | J38: Yes | K38: Enemy/NPC animations. | L38: Asylum patient/inmate animations. | M38: Could have useful animations for the enemies | N38: Collection ↗ | O38: Asset Store ↗ | Q38: Asylum NPC Animations v1.0 | R38: RamsterZ | S38: 1.0 | T38: 2024-09-10
B39: AST-137 | C39: Female Clown | D39: Animation — Clips & Mocap | E39: Owned | F39: Owned (not in project) | G39: Owned (was P1 · #37) | H39: 19.99 | I39: No | J39: Yes | K39: Daddy's Joke or similar stage enemies. | L39: Bat-wielding thug/clown combat animations and emotes. | M39: Useful animation, probably for daddy's joke or stage tail enemies. | N39: Collection ↗ | O39: Asset Store ↗ | Q39: Female Clown v1.0 | R39: RamsterZ | S39: 1.0 | T39: 2024-09-26
B40: AST-139 | C40: Goblin Anims | D40: Animation — Clips & Mocap | E40: Owned | F40: Owned (not in project) | G40: Owned (was P1 · #39) | H40: 24.99 | I40: No | J40: Yes | K40: A smaller Legion enemy. | L40: Goblin/small biped animations: combat, ambushes, movement. | M40: Could be useful for a smaller type of enemy in Legion, probably the Batman, which I haven't described yet. | N40: Collection ↗ | O40: Asset Store ↗ | Q40: Goblin Anims v1.0 | R40: RamsterZ | S40: 1.0 | T40: 2023-06-12
B41: AST-163 | C41: Female Anim Starter Pack | D41: Animation — Clips & Mocap | E41: Owned | F41: Owned (not in project) | G41: Owned (was P2 · #63) | H41: 15 | I41: No | J41: Yes | K41: General female NPC/enemy clips. | L41: Essential female locomotion and talking animations. | M41: Could have some useful animations | N41: Collection ↗ | O41: Asset Store ↗ | Q41: Female Anim Starter Pack v1.1 | R41: RamsterZ | S41: 1.1 | T41: 2023-01-20
B42: AST-166 | C42: Small Boat Anim Set | D42: Animation — Clips & Mocap | E42: Owned | F42: Owned (not in project) | G42: Owned (was P2 · #66) | H42: 8.99 | I42: No | J42: Yes | K42: Later: water navigation sections. | L42: Rowboat animations: rowing, enter/exit, hits. | M42: Could be useful for later sections of the game where you need to navigate on bodies of water. | N42: Collection ↗ | O42: Asset Store ↗ | Q42: Small Boat Anim Set v1.0 | R42: RamsterZ | S42: 1.0 | T42: 2022-05-31
B43: AST-168 | C43: Swim Mocap Animation | D43: Animation — Clips & Mocap | E43: Owned | F43: Owned (not in project) | G43: Owned (was P2 · #68) | H43: 20 | I43: No | J43: Yes | K43: Later: swimming (Tracey can't enter water in the demo). | L43: 150 mocap swim animations (in place + root motion). | N43: Collection ↗ | O43: Asset Store ↗ | Q43: Swim Mocap Animation v1.0 | R43: Yummy Games | S43: 1.0 | T43: 2022-09-27
B44: AST-289 | C44: Crawling Ghoul Animations | D44: Animation — Clips & Mocap | E44: Owned | F44: Owned (not in project) | G44: Owned (new · not on original list) | H44: 19.99 | I44: No | J44: Yes | K44: Not assigned yet. Crawler enemy locomotion candidate. | L44: Crawling ghoul / creature movement animation clips (horror). | M44: [Claude] Added 2026-10-05 — acquired outside the original list. [Claude] 2026-10-27: downloaded again, byte-identical to the file already owned (v1.1). | N44: Collection ↗ | O44: Asset Store ↗ | Q44: Crawling Ghoul Animations v1.1 | R44: RamsterZ | S44: 1.1 | T44: 2025-11-14
B45: AST-304 | C45: Dance Party - Mocap Animation Pack | D45: Animation — Clips & Mocap | E45: Owned | F45: Owned (not in project) | G45: Owned (new · not on original list) | H45: 24.99 | I45: No | J45: Yes | K45: Not for the demo (1979 Alaska). Other projects. | L45: Nightclub/party dance mocap: about 9 minutes of seamless loops, 120 BPM. | M45: [Claude] Added 2026-10-11 — acquired outside the original list. | N45: Collection ↗ | O45: Asset Store ↗ | Q45: Dance Party - Mocap Animation Pack v2.0 | R45: MoCap Online | S45: 2.0 | T45: 2023-06-30
B46: AST-309 | C46: Flashlight Animation Set | D46: Animation — Clips & Mocap | E46: Owned | F46: Owned (not in project) | G46: Owned (new · not on original list) | H46: 9.99 | I46: No | J46: Yes | K46: Not assigned yet. Candidate for the flashlight in the hands (MRM-44 is a plain toggled light with no animation). Read Docs/hands-items-and-weapons-pipeline.md first. | L46: Flashlight handling animations (survival / horror). | M46: [Claude] Added 2026-10-27 — acquired outside the original list. | N46: Collection ↗ | O46: Asset Store ↗ | Q46: Flashlight Animation Set v1.0 | R46: VanillaLoopStudio | S46: 1.0 | T46: 2025-06-06
B47: AST-319 | C47: Female Zombie Animations | D47: Animation — Clips & Mocap | E47: Owned | F47: Owned (not in project) | G47: Owned (new · not on original list) | H47: 45.99 | I47: No | J47: Yes | K47: Not assigned yet. Female zombie enemy candidate; pairs with AST-121 Zombie Animations Set. | L47: Female zombie animation set: about 217 FBX clips with animator controllers and a demo scene. | M47: [Claude] Added 2026-10-29 — acquired outside the original list. | N47: Collection ↗ | O47: Asset Store ↗ | Q47: Female Zombie Animations v1.0 | R47: RamsterZ | S47: 1.0 | T47: 2025-10-11
B48: AST-136 | C48: Chainsaw Attacks | D48: Animation — Clips & Mocap | E48: Wishlist | F48: Wishlist P1 | G48: P1 · #36 | H48: 15 | I48: No | J48: — | K48: A chainsaw enemy. | L48: Chainsaw attacks and idles. | M48: Useful animation for a chainsaw type of enemy | O48: Asset Store ↗ | R48: RamsterZ | S48: 1.0 | T48: 2022-08-04
B49: AST-138 | C49: Werewolf Animation Set | D49: Animation — Clips & Mocap | E49: Wishlist | F49: Wishlist P1 | G49: P1 · #38 | H49: 39.99 | I49: No | J49: — | K49: The werewolf enemy. | L49: Werewolf/semi-bipedal monster animations with proxy model. | M49: Could have some useful information for the werewolf type of enemy | O49: Asset Store ↗ | R49: RamsterZ | S49: 1.0 | T49: 2022-07-11
B50: AST-029 | C50: Sounds Good - Easy & Optimized Audio Manager | D50: Audio Tools | E50: Owned | F50: Owned | H50: 15 | I50: No | J50: Yes | K50: Adopted as the playback/pool backend for MRM-38 / 39 / 65 — not migrated yet. | L50: Easy, pooled audio manager: sounds, music, playlists, dynamic music with one line of code. | M50: [Claude] 2026-10-11: v2.3.0 downloaded (was 2.2.2); NOT yet synced into the project. | N50: Collection ↗ | O50: Asset Store ↗ | P50: Docs ↗ | Q50: Sounds Good - Easy Optimized Audio Manager v2.3.0 | R50: Melenitas Dev | S50: 2.3.0 | T50: 2026-10-05
B51: AST-030 | C51: Ambient Sounds - Interactive Soundscapes for Unity 6 | D51: Audio Tools | E51: Owned | F51: Owned | H51: 49 | I51: No | J51: Yes | K51: Rejected — MRM-38's own sound-layer system already covers zones. | L51: Interactive, zone-based soundscape system (Procedural Worlds). | N51: Collection ↗ | O51: Asset Store ↗ | P51: Docs ↗ | Q51: Ambient Sounds - Interactive Soundscapes for Unity 6 v1.2.19 | R51: Procedural Worlds Inc | S51: 1.2.19 | T51: 2026-06-30
B52: AST-058 | C52: Survival Horror Game Music Pack | D52: Audio — Music | E52: Owned | F52: Owned | H52: 24.99 | I52: No | J52: Yes | K52: Marked 'NO USE' by you. | L52: Cinematic survival-horror music collection (Dave Deville). | M52: [Claude] Fixed: the original Asset Store link pointed to Screenspace VFX. | N52: Collection ↗ | O52: Asset Store ↗ | Q52: NO USE Survival Horror Game Music Pack v1.0 | R52: Dave Deville | S52: 1.0 | T52: 2019-11-19
B53: AST-075 | C53: Retro Action - 16-bit style Rock & Metal Combat Music Pack | D53: Audio — Music | E53: Owned | F53: Owned | H53: 59.99 | I53: No | J53: Yes | K53: Legion mode music. | L53: 16-bit style rock and metal combat music with loops. | M53: Music useful for the Legion mode | O53: Asset Store ↗ | Q53: Assume the last version. | R53: Rodrigo Flores Music | S53: 1.0 | T53: 2026-08-12
B54: AST-076 | C54: Heavy Action Music Pack – Driving Metal & Combat Themes | D54: Audio — Music | E54: Owned | F54: Owned | H54: 29.99 | I54: No | J54: Yes | K54: Legion mode music. | L54: Driving metal and combat themes with seamless loops. | M54: Music useful for the Legion mode [Claude] 2026-10-01: staged in Playground (PLAYGROUND/AST-076), 60 audio clips, no scene. Pending move to Mr. Moonlight. | O54: Asset Store ↗ | Q54: Assume the last version. | R54: Rodrigo Flores Music | S54: 1.0.2 | T54: 2026-06-17
B55: AST-106 | C55: Free Horror Ambience 2 | D55: Audio — Music | E55: Wishlist | F55: Wishlist P1 | G55: P1 · #6 | H55: 0 | I55: No | J55: — | K55: Tension ambience for story pauses and Legion mode breaks — free. | L55: Free dark horror ambience music. | M55: Could be useful for ambience music. To create tension, could be useful on pauses during the Legion mode or the story mode. | O55: Asset Store ↗ | R55: N91music | S55: 1.0 | T55: 2022-03-17
B56: AST-008 | C56: Guns Sounds - Sound Effects | D56: Audio — SFX & Ambience | E56: Owned | F56: Owned | H56: 4.99 | I56: No | J56: Yes | K56: Playground only. Extra weapon SFX layers for MRM-22 / MRM-24 if HQ FPS Weapons' audio falls short. | L56: Small pack of firearm shot / reload sound effects. | N56: Collection ↗ | O56: Asset Store ↗ | Q56: Guns Sounds - Sound Effects v1.0 | R56: AD Sounds | S56: 1.0 | T56: 2025-06-22
B57: AST-010 | C57: Outdoor Atmospheres Sound Effects Pack | D57: Audio — SFX & Ambience | E57: Owned | F57: Owned | H57: 25 | I57: No | J57: Yes | K57: Adopted for MRM-38 sound layers (forest/tundra beds). Import compressed, never WAV. | L57: 60+ outdoor soundscapes: forests, tundra, mountains, swamp, snow and fantasy lands. | N57: Collection ↗ | O57: Asset Store ↗ | P57: Docs ↗ | Q57: Outdoor Atmospheres Sound Effects Pack v2.0 | R57: Olivier Girardot | S57: 2.0 | T57: 2020-12-29
B58: AST-095 | C58: Underground Atmospheres Sound Effects Pack 2021 | D58: Audio — SFX & Ambience | E58: Owned | F58: Owned (added later) | H58: 29.99 | I58: No | J58: Unknown | K58: Adopted for MRM-38 mine sound layers. | L58: Underground ambiences: tunnels, sewers, caves, ice caverns. | M58: [Claude] Added — found in the project / project docs, was not on the list. | O58: Asset Store ↗ | P58: Docs ↗ | Q58: Owned (per project docs) | R58: Olivier Girardot | S58: 2.0 | T58: 2021-05-24
B59: AST-110 | C59: The Complete UI Sound Effects Library | D59: Audio — SFX & Ambience | E59: Owned | F59: Owned (not in project) | G59: Owned (was P1 · #10) | H59: 39.98 | I59: No | J59: Yes | K59: Menu and HUD sounds (MRM-18 and beyond). | L59: 500+ professionally mastered UI sounds. | M59: Must review to use samples on the UI of MrMoonlight. | N59: Collection ↗ | O59: Asset Store ↗ | Q59: The Complete UI Sound Effects Library v1.0.1 | R59: Celeris Lab | S59: 1.0.1 | T59: 2025-09-23
B60: AST-111 | C60: Zombie Voices Audio Pack | D60: Audio — SFX & Ambience | E60: Owned | F60: Owned (not in project) | G60: Owned (was P1 · #11) | H60: 8.99 | I60: No | J60: Yes | K60: Enemy vocalizations (zombies, ferals). | L60: 600+ zombie vocal sounds. | M60: Could be useful for enemy sounds. | N60: Collection ↗ | O60: Asset Store ↗ | Q60: Zombie Voices Audio Pack v1.0 | R60: Yummy Games | S60: 1.0 | T60: 2022-05-16
B61: AST-112 | C61: Monster Sounds - Volume II | D61: Audio — SFX & Ambience | E61: Owned | F61: Owned (not in project) | G61: Owned (was P1 · #12) | H61: 20 | I61: No | J61: Yes | K61: Enemy vocalizations. | L61: Terrifying monster roars, growls and screams. | M61: Could have some useful sounds for the enemies | N61: Collection ↗ | O61: Asset Store ↗ | P61: Docs ↗ | Q61: Monster Sounds - Volume II v2.0 (16 May 2026) | R61: AD Sounds | S61: 2.0 | T61: 2026-05-15
B62: AST-150 | C62: Combat Magic Spells - Sound Effects | D62: Audio — SFX & Ambience | E62: Owned | F62: Owned (not in project) | G62: Owned (was P2 · #50) | H62: 19.99 | I62: No | J62: Yes | K62: Enemy special attacks and Legion mode. | L62: Combat magic and spell sound effects. | M62: Contains sensors and sounds that we can use for enemies and Legion mode. | N62: Collection ↗ | O62: Asset Store ↗ | Q62: Combat Magic Spells - Sound Effects v3.0 | R62: AD Sounds | S62: 3.0 | T62: 2026-06-05
B63: AST-151 | C63: Monster Sounds Pack | D63: Audio — SFX & Ambience | E63: Owned | F63: Owned (not in project) | G63: Owned (was P2 · #51) | H63: Not listed | I63: No | J63: Unknown | K63: Enemy vocalizations. | L63: Monster sounds pack. | M63: Could have some useful sounds for the enemies [Claude] No matching Asset Store listing found — likely delisted. | N63: Collection ↗ | Q63: Monster Sounds Pack v1.0
B64: AST-152 | C64: Guns Sound Essentials | D64: Audio — SFX & Ambience | E64: Owned | F64: Owned (not in project) | G64: Owned (was P2 · #52) | H64: Not listed | I64: No | J64: Unknown | K64: Weapon sound layers. | L64: Essential gun sound effects. | M64: Could have useful sounds for the weapons [Claude] No matching Asset Store listing found — likely delisted. | N64: Collection ↗ | Q64: Guns Sound Essentials v1.0
B65: AST-273 | C65: Essential Footsteps SFX | D65: Audio — SFX & Ambience | E65: Owned | F65: Owned (not in project) | G65: Owned (new · not on original list) | H65: 5 | I65: No | J65: Yes | K65: Not assigned yet. Candidate for player and enemy footsteps. | L65: Foley footstep sound effects for a range of surfaces. | M65: [Claude] Added 2026-09-29 — acquired outside the original list. | N65: Collection ↗ | O65: Asset Store ↗ | Q65: Essential Footsteps SFX v1.1 | R65: Sound Kajiya | S65: 1.1 | T65: 2026-05-14
B66: AST-276 | C66: Sci-Fi Game Sound Effects | D66: Audio — SFX & Ambience | E66: Owned | F66: Owned (not in project) | G66: Owned (new · not on original list) | H66: 29.99 | I66: No | J66: Yes | K66: Not assigned yet. Other projects (sci-fi). | L66: Sci-fi sound effects library. | M66: [Claude] Added 2026-09-29 — acquired outside the original list. | N66: Collection ↗ | O66: Asset Store ↗ | Q66: Sci-Fi Game Sound Effects v1.0 | R66: Magic Sound Effects | S66: 1.0 | T66: 2023-09-18
B67: AST-279 | C67: Ultimate Sound FX Bundle | D67: Audio — SFX & Ambience | E67: Owned | F67: Owned (not in project) | G67: Owned (new · not on original list) | H67: Unknown | I67: No | J67: Unknown | K67: Not assigned yet. Candidate SFX source. | L67: Large sound effects bundle. | M67: [Claude] Added 2026-09-29 — acquired outside the original list. No store page: publisher, price and version unknown. | N67: Collection ↗ | O67: Not on the Asset Store | Q67: Ultimate Sound FX Bundle v2.1 | R67: Unknown | S67: Unknown | T67: Unknown
B68: AST-298 | C68: Horror Bundle - Sound Effects | D68: Audio — SFX & Ambience | E68: Owned | F68: Owned (not in project) | G68: Owned (new · not on original list) | H68: 49.99 | I68: No | J68: No | K68: Not assigned yet. Horror SFX candidate (creepy, doors, female voice, gore, zombie, ghost). Staged in Playground 2026-10-07 as 'AST-298 (Horror Sounds)'. | L68: Horror sound effects bundle: creepy ambiences, doors, female voice, gore, zombie and ghost sounds. | M68: [Claude] Added 2026-10-07 — acquired outside the original list. Import only: 3,284 audio clips, audio workflow not run. Not in Mr. Moonlight. | N68: Collection ↗ | O68: Asset Store ↗ | Q68: Horror Bundle - Sound Effects v8.0 | R68: AD Sounds | S68: 10.0 | T68: 2026-07-16
B69: AST-185 | C69: JiggleMaker | D69: Blender Add-ons | E69: Wishlist | F69: Wishlist P3 | G69: P3 · #85 | H69: See source | I69: No | J69: — | K69: Not needed for the demo. | L69: Blender add-on for natural jiggle physics on meshes and rigs. | M69: [Claude] Superhive blocked automated reading — check the price on the page. | O69: Superhive ↗ | R69: Lewdineer (Superhive)
B70: AST-186 | C70: JiggleGen | D70: Blender Add-ons | E70: Wishlist | F70: Wishlist P3 | G70: P3 · #86 | H70: See source | I70: No | J70: — | K70: Not needed for the demo. | L70: Blender add-on that automates cloth-sim proxy meshes for hair, ears and accessories. | M70: [Claude] Superhive blocked automated reading — check the price on the page. | O70: Superhive ↗ | R70: PathNode (Superhive)
B71: AST-062 | C71: Forest animals 2.0 | D71: Characters — Animals | E71: Owned | F71: Owned | H71: 200 | I71: No | J71: Yes | K71: Island wildlife (deer, bears, etc.). The wolf is covered by another asset. | L71: 77 variations of 8 wild animal types, fully animated. | M71: A lot of animals that can be useful for integrating them into the game there is also a wolf but the wolf will be covered with another asset. | N71: Collection ↗ | O71: Asset Store ↗ | Q71: Forest animals 2.0 v1.1 | R71: Red Deer | S71: 1.1 | T71: 2023-11-11
B72: AST-097 | C72: Wolf_enemu | D72: Characters — Animals | E72: Owned | F72: Owned (added later) | H72: 4.99 | I72: No | J72: Unknown | K72: Wolf enemy candidate (MRM-33) — staged in Playground. | L72: Low-poly animated wolf. | M72: [Claude] Added — found in the project / project docs, was not on the list. | O72: Asset Store ↗ | Q72: Owned (per project docs) | R72: As_Alex | S72: 1.0 | T72: 2021-06-10
B73: AST-117 | C73: Cat - Simple | D73: Characters — Animals | E73: Owned | F73: Owned (not in project) | G73: Owned (was P1 · #17) | H73: 25 | I73: No | J73: Yes | K73: Mr. Whiskers (the cat). | L73: Realistic simple cats with 100+ animations, 6 colours. | M73: Could be useful for Mr. Whiskers' character in Mr. Moonlight, which is a cat. | N73: Collection ↗ | O73: Asset Store ↗ | Q73: Cat - Simple v3.0 (04 Feb 2023) | R73: Red Deer | S73: 3.0 | T73: 2023-02-03
B74: AST-155 | C74: Cats pack | D74: Characters — Animals | E74: Owned | F74: Owned (not in project) | G74: Owned (was P2 · #55) | H74: 50 | I74: No | J74: Yes | K74: Mr. Whiskers — bigger variant of Cat Simple (pick one). | L74: Realistic cats with 100+ animations, 4 builds, 21 colours. | M74: Could be useful for Mr. Whiskers' character in Mr. Moonlight, which is a cat. | N74: Collection ↗ | O74: Asset Store ↗ | Q74: Cats pack v2.0 | R74: Red Deer | S74: 2.0 | T74: 2023-03-09
B75: AST-230 | C75: Cats - Strays | D75: Characters — Animals | E75: Owned | F75: Owned (not in project) | G75: Owned (was P4 · #130) | H75: 25 | I75: No | J75: Yes | K75: Scruffy alternative for Mr. Whiskers. | L75: Realistic stray cats with 100+ animations. | N75: Collection ↗ | O75: Asset Store ↗ | Q75: Cats - Strays v1.0 | R75: Red Deer | S75: 1.0 | T75: 2023-02-21
B76: AST-067 | C76: Anime Girls Pack | D76: Characters — Anime | E76: Owned | F76: Owned | H76: 580 | I76: No | J76: Yes | K76: Personal library — not for Mr. Moonlight. | L76: Bundle of anime girl characters (SURIYUN). | N76: Collection ↗ | O76: Asset Store ↗ | Q76: Anime Girls Pack v3.2 | R76: SURIYUN | S76: 3.2 | T76: 2025-12-15
B77: AST-233 | C77: Gobi Anime Goblin Girl | D77: Characters — Anime | E77: Owned | F77: Owned (not in project) | G77: Owned (was P5 · #133) | H77: 15 | I77: No | J77: Yes | K77: Not for Mr. Moonlight. | L77: Anime fantasy goblin girl. | N77: Collection ↗ | O77: Asset Store ↗ | Q77: Gobi Anime Goblin Girl v1.0 | R77: smoky_fox | S77: 1.0 | T77: 2025-05-15
B78: AST-234 | C78: Anime Style Girl: Haruka | D78: Characters — Anime | E78: Owned | F78: Owned (not in project) | G78: Owned (was P5 · #134) | H78: Not listed | I78: No | J78: Unknown | K78: Not for Mr. Moonlight. | L78: Anime-style girl Haruka with 10 outfit prefabs. | M78: [Claude] No Asset Store listing found — likely delisted. | N78: Collection ↗ | Q78: Anime Style Girl Haruka v1.1
B79: AST-237 | C79: Aoi Character Pack | D79: Characters — Anime | E79: Owned | F79: Owned (not in project) | G79: Owned (was P5 · #137) | H79: 35 | I79: No | J79: No | K79: Not for Mr. Moonlight. | L79: Japanese anime-style character set (Aoi). | M79: [Claude] Merged duplicate (was listed twice). | N79: Collection ↗ | O79: Asset Store ↗ | Q79: Aoi Character Pack v1.11 | R79: Game Asset Studio | S79: 1.16 | T79: 2018-03-09
B80: AST-238 | C80: Honoka Futaba Basic Set | D80: Characters — Anime | E80: Owned | F80: Owned (not in project) | G80: Owned (was P5 · #138) | H80: 35 | I80: No | J80: No | K80: Not for Mr. Moonlight. | L80: Japanese anime-style character set (Honoka Futaba). | N80: Collection ↗ | O80: Asset Store ↗ | Q80: Honoka Futaba Basic Set v1.17 | R80: Game Asset Studio | S80: 1.18 | T80: 2018-03-09
B81: AST-240 | C81: Survivor Girl 1 | D81: Characters — Gooner | E81: Owned | F81: Owned (not in project) | G81: Owned (was P5 · #140) | H81: 39.99 | I81: No | J81: Yes | K81: Not for Mr. Moonlight. | L81: Low-poly survivor girl, usable as heroine or zombie girl. | N81: Collection ↗ | O81: Asset Store ↗ | Q81: Survivor Girl 1 v1.1 | R81: SDKwarrior | S81: 1.1 | T81: 2022-01-25
B82: AST-241 | C82: Mechanic Girl Modular | D82: Characters — Gooner | E82: Owned | F82: Owned (not in project) | G82: Owned (was P5 · #141) | H82: 59.99 | I82: No | J82: Yes | K82: Not for Mr. Moonlight. | L82: Modular mechanic girl, humanoid rig, blendshapes. | N82: Collection ↗ | O82: Asset Store ↗ | P82: Docs ↗ | Q82: Mechanic Girl Modular v1.1 | R82: Ida Faber | S82: 1.1 | T82: 2026-02-05
B83: AST-242 | C83: Vampire Girl Modular | D83: Characters — Gooner | E83: Owned | F83: Owned (not in project) | G83: Owned (was P5 · #142) | H83: 59.99 | I83: No | J83: No | K83: Not for Mr. Moonlight. | L83: Modular vampire girl with blendshapes. | N83: Collection ↗ | O83: Asset Store ↗ | P83: Docs ↗ | Q83: Vampire Girl Modular v1.0 | R83: Ida Faber | S83: 1.1 | T83: 2023-11-20
B84: AST-243 | C84: Dryad Girl Fawnia | D84: Characters — Gooner | E84: Owned | F84: Owned (not in project) | G84: Owned (was P5 · #143) | H84: 89.99 | I84: No | J84: Yes | K84: Not for Mr. Moonlight. | L84: Dryad girl Fawnia, fantasy character. | N84: Collection ↗ | O84: Asset Store ↗ | P84: Docs ↗ | Q84: Dryad Girl Fawnia v1.0 | R84: Ida Faber | S84: 1.0 | T84: 2023-06-23
B85: AST-244 | C85: Cosmo Dragon Girl | D85: Characters — Gooner | E85: Owned | F85: Owned (not in project) | G85: Owned (was P5 · #144) | H85: 89.99 | I85: No | J85: No | K85: Not for Mr. Moonlight. | L85: Modular cosmo dragon girl, humanoid rig, blendshapes. | N85: Collection ↗ | O85: Asset Store ↗ | P85: Docs ↗ | Q85: Cosmo Dragon Girl v2.0 | R85: Ida Faber | S85: 2.0.1 | T85: 2025-06-08
B86: AST-245 | C86: Cyberpunk Ninja Girl Vex | D86: Characters — Gooner | E86: Owned | F86: Owned (not in project) | G86: Owned (was P5 · #145) | H86: 99.99 | I86: No | J86: Yes | K86: Not for Mr. Moonlight. | L86: Cyberpunk ninja girl Vex with advanced shaders. | N86: Collection ↗ | O86: Asset Store ↗ | P86: Docs ↗ | Q86: Cyberpunk Ninja Girl Vex v1.0 | R86: Ida Faber | S86: 1.0 | T86: 2024-08-31
B87: AST-246 | C87: K-POP SERIES: Mina | D87: Characters — Gooner | E87: Owned | F87: Owned (not in project) | G87: Owned (was P5 · #146) | H87: 149.99 | I87: No | J87: No | K87: Not for Mr. Moonlight. | L87: K-pop girl Mina with 3 outfits. | N87: Collection ↗ | O87: Asset Store ↗ | P87: Docs ↗ | Q87: K-POP SERIES Mina v1.0 | R87: Ida Faber | S87: 1.2 | T87: 2023-11-14
B88: AST-247 | C88: Gamer Girl | D88: Characters — Gooner | E88: Owned | F88: Owned (not in project) | G88: Owned (was P5 · #147) | H88: 149.99 | I88: No | J88: Yes | K88: Not for Mr. Moonlight. | L88: Stylized gamer girl character with outfits. | M88: Staged in Playground 2026-10-07 as 'AST-247 (Gamer Girl)'. Render audit 2026-10-07: URP set renders (15 prefabs, 0 pink); the Built-in and HDRP folders are the vendor's other variants (pink in URP by design). Not in Mr. Moonlight. | N88: Collection ↗ | O88: Asset Store ↗ | P88: Docs ↗ | Q88: Gamer Girl v1.0 | R88: Ida Faber | S88: 1.0 | T88: 2022-11-19
B89: AST-248 | C89: Customizable School Girls | D89: Characters — Gooner | E89: Owned | F89: Owned (not in project) | G89: Owned (was P5 · #148) | H89: 89.99 | I89: No | J89: Yes | K89: Not for Mr. Moonlight. | L89: Customizable school girls. | N89: Collection ↗ | O89: Asset Store ↗ | Q89: Customizable School Girls v1.0 | R89: Ida Faber | S89: 1.0 | T89: 2021-07-20
B90: AST-249 | C90: Ami | D90: Characters — Gooner | E90: Owned | F90: Owned (not in project) | G90: Owned (was P5 · #149) | H90: 39 | I90: No | J90: No | K90: Not for Mr. Moonlight. | L90: Ami — anime character with bikini and school uniform. | M90: [Claude] 2026-10-02: downloaded as 'Ami Bikini School Uniform' v1.2 (same product as this row; the store lists it as 'Ami', 3.1). | N90: Collection ↗ | O90: Asset Store ↗ | Q90: Ami Bikini School Uniform v1.2 | R90: SURIYUN | S90: 3.1 | T90: 2025-12-16
B91: AST-250 | C91: Anime Girl Characters - Bikini | D91: Characters — Gooner | E91: Owned | F91: Owned (not in project) | G91: Owned (was P5 · #150) | H91: Not listed | I91: No | J91: Unknown | K91: Not for Mr. Moonlight. | L91: Anime girl characters in bikinis (Lukebox). | M91: [Claude] Merged duplicate. No working Asset Store link found. [Claude] 2026-09-30: downloaded v1.0; no store page, so version check is Unknown. | N91: Collection ↗ | Q91: Anime Girl Characters - Bikini v1.0 | R91: Lukebox
B92: AST-251 | C92: SuccubusV | D92: Characters — Gooner | E92: Owned | F92: Owned (not in project) | G92: Owned (was P5 · #151) | H92: 16 | I92: No | J92: Yes | K92: Not for Mr. Moonlight. | L92: Three low-poly succubus characters with 12 animations. | N92: Collection ↗ | O92: Asset Store ↗ | Q92: SuccubusV v1.0 | R92: Hit | S92: 1.0 | T92: 2022-10-13
B93: AST-252 | C93: Succubus Sisters: Complete Edition | D93: Characters — Gooner | E93: Owned | F93: Owned (not in project) | G93: Owned (was P5 · #152) | H93: 219.99 | I93: No | J93: Yes | K93: Not for Mr. Moonlight. | L93: Three modular low-poly succubus girls. | N93: Collection ↗ | O93: Asset Store ↗ | P93: Docs ↗ | Q93: Succubus Sisters Complete Edition v1.0 | R93: Ida Faber | S93: 1.0 | T93: 2023-05-01
B94: AST-253 | C94: CombatGirls_TwinKunaiCharacterPack | D94: Characters — Gooner | E94: Wishlist | F94: Wishlist P5 | G94: P5 · #153 | H94: 60 | I94: No | J94: — | K94: Not for Mr. Moonlight. | L94: CombatGirls — twin kunai character + animations. | N94: Collection ↗ | O94: Asset Store ↗ | R94: BIPER | S94: 1.3.1 | T94: 2026-08-14
B95: AST-254 | C95: CombatGirls_GreatSwordCharacterPack | D95: Characters — Gooner | E95: Wishlist | F95: Wishlist P5 | G95: P5 · #154 | H95: 60 | I95: No | J95: — | K95: Not for Mr. Moonlight. | L95: CombatGirls — great sword character + animations. | N95: Collection ↗ | O95: Asset Store ↗ | R95: BIPER | S95: 1.3.1 | T95: 2026-08-14
B96: AST-255 | C96: CombatGirls_SwordShieldCharacterPack | D96: Characters — Gooner | E96: Wishlist | F96: Wishlist P5 | G96: P5 · #155 | H96: 60 | I96: No | J96: — | K96: Not for Mr. Moonlight. | L96: CombatGirls — sword & shield character + animations. | N96: Collection ↗ | O96: Asset Store ↗ | R96: BIPER | S96: 1.3.1 | T96: 2026-08-14
B97: AST-256 | C97: CombatGirls_RifleCharacterPack | D97: Characters — Gooner | E97: Wishlist | F97: Wishlist P5 | G97: P5 · #156 | H97: 60 | I97: No | J97: — | K97: Not for Mr. Moonlight. | L97: CombatGirls — rifle character + animations. | N97: Collection ↗ | O97: Asset Store ↗ | R97: BIPER | S97: 1.3.1 | T97: 2026-08-14
B98: AST-257 | C98: CombatGirls_KatanaCharacterPack | D98: Characters — Gooner | E98: Wishlist | F98: Wishlist P5 | G98: P5 · #157 | H98: 60 | I98: No | J98: — | K98: Not for Mr. Moonlight. | L98: CombatGirls — katana character + animations. | M98: [Claude] The publisher labels the current version 'Fonts'. | N98: Collection ↗ | O98: Asset Store ↗ | R98: Fonts | S98: Fonts
B99: AST-258 | C99: CombatGirls_RocketLauncherCharacterPack | D99: Characters — Gooner | E99: Wishlist | F99: Wishlist P5 | G99: P5 · #158 | H99: 60 | I99: No | J99: — | K99: Not for Mr. Moonlight. | L99: CombatGirls — rocket launcher character + animations. | N99: Collection ↗ | O99: Asset Store ↗ | R99: BIPER | S99: 1.3.1 | T99: 2026-08-14
B100: AST-259 | C100: CombatGirls_SwordCharacterPack | D100: Characters — Gooner | E100: Wishlist | F100: Wishlist P5 | G100: P5 · #159 | H100: 60 | I100: No | J100: — | K100: Not for Mr. Moonlight. | L100: CombatGirls — sword character + animations. | N100: Collection ↗ | O100: Asset Store ↗ | R100: BIPER | S100: 1.3.1 | T100: 2026-08-14
...

Sheet By Category
B2: category | C2: owned | D2: wishlist | E2: total | F2: in Mr Moonlight (Yes)
B3: AI & Behavior | C3: =COUNTIFS('Browse by Category'!$D$3:$D$317,$B3,'Browse by Category'!$E$3:$E$317,"Owned") | D3: =COUNTIFS('Browse by Category'!$D$3:$D$317,$B3,'Browse by Category'!$E$3:$E$317,"Wishlist") | E3: =C3+D3 | F3: =COUNTIFS('Browse by Category'!$D$3:$D$317,$B3,'Browse by Category'!$I$3:$I$317,"Yes*")
B4: Animation & Rigging Tools | C4: =COUNTIFS('Browse by Category'!$D$3:$D$317,$B4,'Browse by Category'!$E$3:$E$317,"Owned") | D4: =COUNTIFS('Browse by Category'!$D$3:$D$317,$B4,'Browse by Category'!$E$3:$E$317,"Wishlist") | E4: =C4+D4 | F4: =COUNTIFS('Browse by Category'!$D$3:$D$317,$B4,'Browse by Category'!$I$3:$I$317,"Yes*")
B5: Animation — Clips & Mocap | C5: =COUNTIFS('Browse by Category'!$D$3:$D$317,$B5,'Browse by Category'!$E$3:$E$317,"Owned") | D5: =COUNTIFS('Browse by Category'!$D$3:$D$317,$B5,'Browse by Category'!$E$3:$E$317,"Wishlist") | E5: =C5+D5 | F5: =COUNTIFS('Browse by Category'!$D$3:$D$317,$B5,'Browse by Category'!$I$3:$I$317,"Yes*")
B6: Audio Tools | C6: =COUNTIFS('Browse by Category'!$D$3:$D$317,$B6,'Browse by Category'!$E$3:$E$317,"Owned") | D6: =COUNTIFS('Browse by Category'!$D$3:$D$317,$B6,'Browse by Category'!$E$3:$E$317,"Wishlist") | E6: =C6+D6 | F6: =COUNTIFS('Browse by Category'!$D$3:$D$317,$B6,'Browse by Category'!$I$3:$I$317,"Yes*")
B7: Audio — Music | C7: =COUNTIFS('Browse by Category'!$D$3:$D$317,$B7,'Browse by Category'!$E$3:$E$317,"Owned") | D7: =COUNTIFS('Browse by Category'!$D$3:$D$317,$B7,'Browse by Category'!$E$3:$E$317,"Wishlist") | E7: =C7+D7 | F7: =COUNTIFS('Browse by Category'!$D$3:$D$317,$B7,'Browse by Category'!$I$3:$I$317,"Yes*")
B8: Audio — SFX & Ambience | C8: =COUNTIFS('Browse by Category'!$D$3:$D$317,$B8,'Browse by Category'!$E$3:$E$317,"Owned") | D8: =COUNTIFS('Browse by Category'!$D$3:$D$317,$B8,'Browse by Category'!$E$3:$E$317,"Wishlist") | E8: =C8+D8 | F8: =COUNTIFS('Browse by Category'!$D$3:$D$317,$B8,'Browse by Category'!$I$3:$I$317,"Yes*")
B9: Blender Add-ons | C9: =COUNTIFS('Browse by Category'!$D$3:$D$317,$B9,'Browse by Category'!$E$3:$E$317,"Owned") | D9: =COUNTIFS('Browse by Category'!$D$3:$D$317,$B9,'Browse by Category'!$E$3:$E$317,"Wishlist") | E9: =C9+D9 | F9: =COUNTIFS('Browse by Category'!$D$3:$D$317,$B9,'Browse by Category'!$I$3:$I$317,"Yes*")
B10: Characters — Animals | C10: =COUNTIFS('Browse by Category'!$D$3:$D$317,$B10,'Browse by Category'!$E$3:$E$317,"Owned") | D10: =COUNTIFS('Browse by Category'!$D$3:$D$317,$B10,'Browse by Category'!$E$3:$E$317,"Wishlist") | E10: =C10+D10 | F10: =COUNTIFS('Browse by Category'!$D$3:$D$317,$B10,'Browse by Category'!$I$3:$I$317,"Yes*")
B11: Characters — Anime | C11: =COUNTIFS('Browse by Category'!$D$3:$D$317,$B11,'Browse by Category'!$E$3:$E$317,"Owned") | D11: =COUNTIFS('Browse by Category'!$D$3:$D$317,$B11,'Browse by Category'!$E$3:$E$317,"Wishlist") | E11: =C11+D11 | F11: =COUNTIFS('Browse by Category'!$D$3:$D$317,$B11,'Browse by Category'!$I$3:$I$317,"Yes*")
B12: Characters — Gooner | C12: =COUNTIFS('Browse by Category'!$D$3:$D$317,$B12,'Browse by Category'!$E$3:$E$317,"Owned") | D12: =COUNTIFS('Browse by Category'!$D$3:$D$317,$B12,'Browse by Category'!$E$3:$E$317,"Wishlist") | E12: =C12+D12 | F12: =COUNTIFS('Browse by Category'!$D$3:$D$317,$B12,'Browse by Category'!$I$3:$I$317,"Yes*")
B13: Characters — Horror & Creatures | C13: =COUNTIFS('Browse by Category'!$D$3:$D$317,$B13,'Browse by Category'!$E$3:$E$317,"Owned") | D13: =COUNTIFS('Browse by Category'!$D$3:$D$317,$B13,'Browse by Category'!$E$3:$E$317,"Wishlist") | E13: =C13+D13 | F13: =COUNTIFS('Browse by Category'!$D$3:$D$317,$B13,'Browse by Category'!$I$3:$I$317,"Yes*")
B14: Characters — Humans & Stylized | C14: =COUNTIFS('Browse by Category'!$D$3:$D$317,$B14,'Browse by Category'!$E$3:$E$317,"Owned") | D14: =COUNTIFS('Browse by Category'!$D$3:$D$317,$B14,'Browse by Category'!$E$3:$E$317,"Wishlist") | E14: =C14+D14 | F14: =COUNTIFS('Browse by Category'!$D$3:$D$317,$B14,'Browse by Category'!$I$3:$I$317,"Yes*")
... B34: Water | C34: =COUNTIFS('Browse by Category'!$D$3:$D$317,$B34,'Browse by Category'!$E$3:$E$317,"Owned") | D34: =COUNTIFS('Browse by Category'!$D$3:$D$317,$B34,'Browse by Category'!$E$3:$E$317,"Wishlist") | E34: =C34+D34 | F34: =COUNTIFS('Browse by Category'!$D$3:$D$317,$B34,'Browse by Category'!$I$3:$I$317,"Yes*")
B35: TOTAL | C35: =SUM(C3:C34) | D35: =SUM(D3:D34) | E35: =SUM(E3:E34) | F35: =SUM(F3:F34)

Sheet Asset Index
B1: Asset Index | E1: Updated 2026-10-27 · prices are full (non-sale) store prices in USD · see the Legend sheet
B2: id | C2: asset name | D2: category | E2: description | F2: collection url | G2: asset store / source | H2: price | I2: in Mr Moonlight? | J2: purpose in Mr Moonlight | K2: notes | L2: documentation | M2: downloaded file | N2: up to date? | O2: status | P2: priority | Q2: publisher | R2: latest version (store) | S2: store updated
B3: OWNED — downloaded assets
B4: AST-001 | C4: Gore Simulator | D4: VFX — Blood & Gore | E4: Runtime dismemberment, cuts and gore meshes for any skinned character. | F4: Collection ↗ | G4: Asset Store ↗ | H4: 65.95 | I4: Yes | J4: MRM-32 / MRM-36 / MRM-37 — limb cutting on enemies. The Spotter already uses it (GoreStorage_Spotter). Vendor code lives in _Project/Code/Vendor/Gore Simulator. | L4: Docs ↗ | M4: Gore Simulator v1.8.8 | N4: Yes | O4: Owned | Q4: Pampel Games | R4: 1.8.8 | S4: 2026-06-28
B5: AST-002 | C5: InfiniCLOUD HDRP - URP, Volumetric clouds & particles | D5: Sky & Atmosphere | E5: Performance-focused volumetric cloud meshes and cloud particles for URP/HDRP. | F5: Collection ↗ | G5: Asset Store ↗ | H5: 49 | I5: Yes | J5: Installed (InfiniCloud URP – single-mesh clouds): cloud layer in the island sky. | M5: InfiniCLOUD HDRP - URP Volumetric clouds particles v2.0.4 (22 Dec 2025) | N5: No | O5: Owned | Q5: ARTnGAME | R5: 2.0.5 | S5: 2026-06-23
B6: AST-003 | C6: Dynamic Radial Masks | D6: Shaders & Post-Processing | E6: Shader extension that projects animated world-space radial masks (ripples, reveals, dissolves) onto any material. | F6: Collection ↗ | G6: Asset Store ↗ | H6: 35 | I6: Yes | J6: MRM-18 — drives the ported rain-ripple effect on water/ground. Vendor code in _Project/Code/Vendor. ⚠ Ripple count is baked into the shader (only 8/64/200 work). | L6: Docs ↗ | M6: Dynamic Radial Masks v2025.3 (18 Dec 2025) | N6: No | O6: Owned | Q6: Amazing Аssets | R6: 2026.5 | S6: 2026-09-05
B7: AST-004 | C7: Cartoon Rain & Blood Rain | D7: VFX — Particles | E7: Rain particle systems (drops, ripples, splashes) including a blood-rain variant; Wind Zone aware. | F7: Collection ↗ | G7: Asset Store ↗ | H7: 6.99 | I7: Yes | J7: Rain particles for the island and main-menu staging (MRM-18). The blood-rain variant is a candidate for Legion mode. | M7: Cartoon Rain Blood Rain v1.1 | N7: Yes | O7: Owned | Q7: BG Studio | R7: 1.1 | S7: 2022-07-25
B8: AST-005 | C8: Shiny SSR 2 - Screen Space Reflections | D8: Shaders & Post-Processing | E8: Screen-space reflections post effect with quality/performance controls (Kronnect). | F8: Collection ↗ | G8: Asset Store ↗ | H8: 51.99 | I8: No | J8: Tried for water reflections in MRM-18, then removed — Crest planar reflections replaced it. | L8: Docs ↗ | M8: Shiny SSR 2 - Screen Space Reflections v32.3.1 | N8: No | O8: Owned | Q8: Kronnect | R8: 32.4.1 | S8: 2026-08-24
B9: AST-006 | C9: PIDI - Planar Reflections 6: URP Edition. | D9: Shaders & Post-Processing | E9: Real-time planar reflections for flat surfaces (mirrors, floors, water). | F9: Collection ↗ | G9: Asset Store ↗ | H9: 40 | I9: No | J9: Evaluated only. Crest handles water reflections now; could still serve mirrors/wet floors in interiors. | K9: [Claude] You own v5 Personal; the store link is PIDI 6 URP, a separate new product (not a free update). | L9: Docs ↗ | M9: PIDI Planar Reflections 5 - Personal Edition v5.4.1 | N9: No | O9: Owned | Q9: Irreverent Software - PIDI | R9: 6.2.8 | S9: 2026-08-07
B10: AST-007 | C10: URP Mirror Shaders / AR-VR Ready | D10: Shaders & Post-Processing | E10: Mirror/reflection shaders for URP including AR/VR support (AkilliMum). | F10: Collection ↗ | G10: Asset Store ↗ | H10: 25 | I10: No | J10: Playground evaluation only. Possible use: mirrors in the cabin or church interiors. | L10: Docs ↗ | M10: URP Mirror Shaders AR-VR Ready v5.11 | N10: No | O10: Owned | Q10: Akıllı Mum | R10: 5.13 | S10: 2025-02-03
B11: AST-008 | C11: Guns Sounds - Sound Effects | D11: Audio — SFX & Ambience | E11: Small pack of firearm shot / reload sound effects. | F11: Collection ↗ | G11: Asset Store ↗ | H11: 4.99 | I11: No | J11: Playground only. Extra weapon SFX layers for MRM-22 / MRM-24 if HQ FPS Weapons' audio falls short. | M11: Guns Sounds - Sound Effects v1.0 | N11: Yes | O11: Owned | Q11: AD Sounds | R11: 1.0 | S11: 2025-06-22
B12: AST-009 | C12: Damage Numbers Pro | D12: UI & HUD | E12: Spawns animated number/text popups (damage, crits, pickups) with 2–3 lines of code. | F12: Collection ↗ | G12: Asset Store ↗ | H12: 7.99 | I12: Yes | J12: Installed with vendor code — floating hit/damage numbers. | M12: Damage Numbers Pro v4.56 | N12: Yes | O12: Owned | Q12: Ekincan Tas | R12: 4.56 | S12: 2026-08-29
B13: AST-010 | C13: Outdoor Atmospheres Sound Effects Pack | D13: Audio — SFX & Ambience | E13: 60+ outdoor soundscapes: forests, tundra, mountains, swamp, snow and fantasy lands. | F13: Collection ↗ | G13: Asset Store ↗ | H13: 25 | I13: No | J13: Adopted for MRM-38 sound layers (forest/tundra beds). Import compressed, never WAV. | L13: Docs ↗ | M13: Outdoor Atmospheres Sound Effects Pack v2.0 | N13: Yes | O13: Owned | Q13: Olivier Girardot | R13: 2.0 | S13: 2020-12-29
B14: AST-011 | C14: Industrial Shipping Container Pack | D14: Props & Weapons | E14: High-quality industrial cargo/shipping containers. | F14: Collection ↗ | G14: Asset Store ↗ | H14: 19.99 | I14: No | J14: Adopted for MRM-60 staging (docks, mine infirmary). | M14: Industrial Shipping Container Pack v1.0 | N14: Yes | O14: Owned | Q14: EVOLVE Studio LTD | R14: 1.0 | S14: 2024-08-05
B15: AST-012 | C15: Controller Overlays & Button Kits (3 styles) x9 controllers +keyboard/mouse | D15: UI & HUD | E15: Controller/keyboard button icon kits for 9 popular gamepads, 3 styles. | F15: Collection ↗ | G15: Asset Store ↗ | H15: 19.99 | I15: No | J15: Playground only. Button prompts for gamepad UI (menus, interaction hints). | M15: Controller Overlays Button Kits (3 styles) x8 controllers keyboard mouse v1.9.2 | N15: No | O15: Owned | Q15: nickknacks | R15: 1.9.3 | S15: 2025-08-04
B16: AST-013 | C16: Retarget Pro V5 | D16: Animation & Rigging Tools | E16: Animation retargeting between any rigs (Humanoid or not) with bake-to-clip output (KINEMATION). | F16: Collection ↗ | G16: Asset Store ↗ | H16: 59.99 | I16: No | J16: Deliberately Playground-only: bakes clips for the Wendigo, wolf and Tracey's body (MRM-75 / MRM-36). Only the baked clips migrate, the tool never does. | L16: Docs ↗ | M16: Retarget Pro V5 v5.2.1 | N16: Yes | O16: Owned | Q16: KINEMATION | R16: 5.2.1 | S16: 2026-08-26
B17: AST-014 | C17: Aged Medieval PBR Tools | D17: Props & Weapons | E17: 7 aged PBR farm/medieval tools (shovel, axe, rake, hammer, sickle…). | F17: Collection ↗ | G17: Asset Store ↗ | H17: 4.99 | I17: No | J17: Adopted for MRM-35 — the sickle only. | M17: Aged Medieval PBR Tools v1.01 | N17: Yes | O17: Owned | Q17: BasicCore | R17: 1.01 | S17: 2016-09-26
B18: AST-015 | C18: Ian's Fire Pack | D18: VFX — Particles | E18: 29 drag-and-drop fire prefabs, from candles to burning trees, with sounds. | F18: Collection ↗ | G18: Asset Store ↗ | H18: 30 | I18: Yes | J18: Installed — fire/flame effects (flare, campfires, burning props; MRM-61). | M18: Ians Fire Pack v2.3 | N18: Yes | O18: Owned | Q18: Ian Scilipoti | R18: 2.3 | S18: 2021-04-13
B19: AST-016 | C19: HE - Abandoned Hospital v.2 | D19: Environments & Level Kits | E19: Large modular abandoned-hospital interior kit (URP/HDRP). | F19: Collection ↗ | G19: Asset Store ↗ | H19: 19 | I19: No | J19: Adopted for MRM-60 — the infirmary inside the mine. | K19: [Claude] Store version is now v2.0; you have v1.4. | M19: HE - Abandoned Hospital v1.4 | N19: No | O19: Owned | Q19: Artur G. | R19: 2.0 | S19: 2025-02-07
B20: AST-017 | C20: Realistic Gun VFX (Muzzle Flash, Bullet Impact, Ejections, Gun VFX, VFX) | D20: VFX — Particles | E20: Realistic muzzle flashes, bullet impacts and shell ejections. | F20: Collection ↗ | G20: Asset Store ↗ | H20: 49.99 | I20: No | J20: Lost the muzzle-flash shoot-out to Shots VFX URP (Round 2, R2.3). Impact effects are still usable. | L20: Docs ↗ | M20: Realistic Gun VFX Muzzle Flash Bullet Impact Ejections Gun VFX VFX v1.0 | N20: Yes | O20: Owned | Q20: Hivemind | R20: 1.0 | S20: 2026-03-09
B21: AST-018 | C21: Procedural Lightning - High Performance and Shocking Lightning | D21: VFX — Particles | E21: High-performance procedural lightning bolts, arcs and beams, with sounds. | F21: Collection ↗ | G21: Asset Store ↗ | H21: 20 | I21: No | J21: Adopted for MRM-57 (storm) and MRM-36 (Furman's bolt). | L21: Docs ↗ | M21: Procedural Lightning - High Performance and Shocking Lightning v3.0.3 | N21: Yes | O21: Owned | Q21: Digital Ruby (Jeff Johnson) | R21: 3.0.3 | S21: 2026-08-29
B22: AST-019 | C22: Cult Animations | D22: Animation — Clips & Mocap | E22: 25 motion-captured cult / ritual animations. | F22: Collection ↗ | G22: Asset Store ↗ | H22: 8 | I22: No | J22: Adopted for MRM-59 cult staging scenes. | M22: Cult Animations v1.0 | N22: Yes | O22: Owned | Q22: Gem Gaming Animations | R22: 1.0 | S22: 2024-05-31
B23: AST-020 | C23: Fly Particles + Sound Effects | D23: VFX — Particles | E23: Fly swarm particle systems with buzzing sounds. | F23: Collection ↗ | G23: Asset Store ↗ | H23: 4.99 | I23: No | J23: Adopted for MRM-60 ambience (corpses, rotting areas). | M23: Fly Particle System v1.0.1 | N23: Yes | O23: Owned | Q23: SpeedTutor | R23: 1.0 | S23: 2023-05-15
B24: AST-021 | C24: Artistic: Radial Blur | D24: Shaders & Post-Processing | E24: Artistic radial blur post effect (speed, focus, panic). | F24: Collection ↗ | G24: Asset Store ↗ | H24: 15 | I24: No | J24: Adopted for MRM-54 fear and MRM-53 low health — one shared channel. | M24: Artistic Radial Blur v2.1.2 (03 Sep 2025) | N24: No | O24: Owned | Q24: Fronkon Games | R24: 3.0.1 | S24: 2026-02-22
B25: AST-022 | C25: ANIMSET: 2 HANDED MELEE WEAPON | D25: Animation — Clips & Mocap | E25: Mocap animation set for two-handed melee weapons. | F25: Collection ↗ | G25: Asset Store ↗ | H25: 19.99 | I25: No | J25: Adopted for MRM-23 melee. Also included inside Ultimate Animation Collection. | M25: ANIMSET 2 HANDED MELEE WEAPON v1.5 | N25: No | O25: Owned | Q25: PROTOFACTOR, INC | R25: 1.642 | S25: 2026-07-06
B26: AST-023 | C26: Spice Up: Ghost Vision | D26: Shaders & Post-Processing | E26: 'Ghost vision' full-screen camera effect (Fronkon Spice Up). | F26: Collection ↗ | G26: Asset Store ↗ | H26: 15 | I26: No | J26: Adopted for MRM-55 — morphine effect. | M26: Spice Up Ghost Vision v2.1.0 | N26: No | O26: Owned | Q26: Fronkon Games | R26: 3.0.0 | S26: 2026-03-09
B27: AST-024 | C27: Spice Up: Stoned | D27: Shaders & Post-Processing | E27: 'Stoned' full-screen camera effect (Fronkon Spice Up). | F27: Collection ↗ | G27: Asset Store ↗ | H27: 15 | I27: No | J27: Adopted for MRM-55 — weed effect. | M27: Spice Up Stoned v1.2.0 | N27: No | O27: Owned | Q27: Fronkon Games | R27: 3.0.0 | S27: 2026-03-09
B28: AST-025 | C28: Spice Up: Rain | D28: Shaders & Post-Processing | E28: Raindrops-on-lens screen effect; can emulate blood or oil on the screen. | F28: Collection ↗ | G28: Asset Store ↗ | H28: 15 | I28: No | J28: Adopted for MRM-53 — blood on the lens. | M28: Spice Up Rain v1.2.0 | N28: No | O28: Owned | Q28: Fronkon Games | R28: 3.0.0 | S28: 2026-03-09
B29: AST-026 | C29: Knife_MocapAnimPack_1.1 | D29: Animation — Clips & Mocap | E29: Mocap knife combat animation pack. | F29: Collection ↗ | G29: Asset Store ↗ | H29: 45 | I29: No | J29: Adopted for MRM-35 knife-wielding enemy. | M29: Knife_MocapAnimPack v1.1 (21 Aug 2026) | N29: Yes | O29: Owned | Q29: RIB Studio | R29: 1.1 | S29: 2026-08-24
B30: AST-027 | C30: Spice Up: BodyCam | D30: Shaders & Post-Processing | E30: Police body-camera full-screen effect (fisheye, timestamp, noise). | F30: Collection ↗ | G30: Asset Store ↗ | H30: 15 | I30: No | J30: Adopted for MRM-49 — telescope aperture. | M30: Spice Up BodyCam v2.1.2 (22 Apr 2025) | N30: No | O30: Owned | Q30: Fronkon Games | R30: 3.0.1 | S30: 2026-06-21
B31: AST-028 | C31: Asset Cleaner PRO - Clean | Find References | D31: Editor Tools & Utilities | E31: Finds unused assets and tracks references across the project. | F31: Collection ↗ | G31: Asset Store ↗ | H31: 30 | I31: No | J31: Adopted for MRM-64. ⚠ Use find-references only — never bulk-delete. | M31: Asset Cleaner PRO - Clean Find References v1.51 | N31: Yes | O31: Owned | Q31: GameDev Tools | R31: 1.51 | S31: 2026-07-13
B32: AST-029 | C32: Sounds Good - Easy & Optimized Audio Manager | D32: Audio Tools | E32: Easy, pooled audio manager: sounds, music, playlists, dynamic music with one line of code. | F32: Collection ↗ | G32: Asset Store ↗ | H32: 15 | I32: No | J32: Adopted as the playback/pool backend for MRM-38 / 39 / 65 — not migrated yet. | K32: [Claude] 2026-10-11: v2.3.0 downloaded (was 2.2.2); NOT yet synced into the project. | L32: Docs ↗ | M32: Sounds Good - Easy Optimized Audio Manager v2.3.0 | N32: Yes | O32: Owned | Q32: Melenitas Dev | R32: 2.3.0 | S32: 2026-10-05
B33: AST-030 | C33: Ambient Sounds - Interactive Soundscapes for Unity 6 | D33: Audio Tools | E33: Interactive, zone-based soundscape system (Procedural Worlds). | F33: Collection ↗ | G33: Asset Store ↗ | H33: 49 | I33: No | J33: Rejected — MRM-38's own sound-layer system already covers zones. | L33: Docs ↗ | M33: Ambient Sounds - Interactive Soundscapes for Unity 6 v1.2.19 | N33: Yes | O33: Owned | Q33: Procedural Worlds Inc | R33: 1.2.19 | S33: 2026-06-30
B34: AST-031 | C34: Low Poly Plant Collections | D34: Vegetation & Nature | E34: 50+ stylized hand-painted low-poly plants with LODs. | F34: Collection ↗ | G34: Asset Store ↗ | H34: 16.99 | I34: Yes | J34: MRM-70 island vegetation (Art/Environment/Vegetation/LowPolyPlants). | M34: Low Poly Plant Collections v2.1 (11 Jul 2023) | N34: Yes | O34: Owned | Q34: Gamester | R34: 2.1 | S34: 2023-07-11
B35: AST-032 | C35: Volumetric Light Beam | D35: Shaders & Post-Processing | E35: Efficient volumetric light-beam cones for spotlights. | F35: Collection ↗ | G35: Asset Store ↗ | H35: 44.9 | I35: No | J35: Parked for MRM-44 flashlight beams — test HAZE alone first. | L35: Docs ↗ | M35: Volumetric Light Beam v2.2.8 | N35: No | O35: Owned | Q35: Tech Salad | R35: 2.2.9 | S35: 2026-09-04
B36: AST-033 | C36: Flying Birds VFX | D36: VFX — Particles | E36: 3D birds that fly in loops around a point, alternating glide and flap. | F36: Collection ↗ | G36: Realtime VFX Store ↗ | H36: 15 | I36: Yes | J36: Installed with vendor code — ambient bird flocks over the island (MRM-59). | M36: Flying Birds VFX v1.0 | N36: Yes | O36: Owned | Q36: Realtime VFX Store | R36: 1.0
B37: AST-034 | C37: Insect VFX [HDRP, URP] | D37: VFX — Particles | E37: VFX Graph insect swarms: cockroaches, moths, flies. | F37: Collection ↗ | G37: Asset Store ↗ | H37: 14.99 | I37: No | J37: Adopted for MRM-60 / MRM-61 ambience. | L37: Docs ↗ | M37: Insect VFX HDRP URP v3.0.0 | N37: Yes | O37: Owned | Q37: Paulina VFX | R37: 3.0.0 | S37: 2026-06-15
B38: AST-035 | C38: HQ Realistic explosions | D38: VFX — Particles | E38: 26 realistic explosions with 4 custom shaders. | F38: Collection ↗ | G38: Asset Store ↗ | H38: 15 | I38: No | J38: Adopted for MRM-57. | M38: HQ Realistic explosions v2.1.0 (10 Nov 2024) | N38: Yes | O38: Owned | Q38: Hovl Studio | R38: 2.1.0 | S38: 2024-11-09
B39: AST-036 | C39: Bullet Impact VFX and Bullet Hole Decals With Sounds | D39: VFX — Particles | E39: Bullet impact particles, bullet-hole decals and impact sounds per surface. | F39: Collection ↗ | G39: Asset Store ↗ | H39: 39.99 | I39: No | J39: Adopted for MRM-22 / MRM-24 impacts + decals (shares a surface lookup with MRM-39). | M39: Bullet Impact VFX and Bullet Hole Decals With Sounds v1.9 (22 Dec 2025) | N39: Yes | O39: Owned | Q39: Medartimus | R39: V.1.9 | S39: 2025-12-22
B40: AST-037 | C40: Shots VFX - URP | D40: VFX — Particles | E40: Stylized gunshot / muzzle flash VFX for URP. | F40: Collection ↗ | G40: Asset Store ↗ | H40: 34.97 | I40: No | J40: Won the muzzle-flash call (R2.3) for MRM-22 / 24 / 52 — migration still pending. | M40: Shots VFX - URP v1.0.21 | N40: Yes | O40: Owned | Q40: Vefects | R40: 1.0.21 | S40: 2026-01-07
B41: AST-038 | C41: FPS Engine | D41: FPS Frameworks & Templates | E41: Full FPS framework (cowsins): movement, weapons, pickups, UI. | F41: Collection ↗ | G41: Asset Store ↗ | H41: 29.99 | I41: No | J41: Rejected as a foundation — kept in Playground as a read-only reference and parts donor. | M41: FPS Engine v1.5.10 | N41: No | O41: Owned | Q41: Cowsins | R41: 1.6 | S41: 2026-09-13
B42: AST-039 | C42: Body Poser - It's dead simple | D42: Editor Tools & Utilities | E42: Pose humanoid models directly in the editor, then bake them static. | F42: Collection ↗ | G42: Asset Store ↗ | H42: 5.99 | I42: No | J42: Adopted for MRM-59 staging (corpses, posed NPCs). Editor-only, zero runtime cost. | M42: Body Poser - Its dead simple v1.4 | N42: Yes | O42: Owned | Q42: RevolvingGearStudios | R42: Body Poser 1.4 | S42: 2026-01-26
B43: AST-040 | C43: Blood Factory | D43: VFX — Blood & Gore | E43: Customizable blood effects: spurts, drips, pools and decals (Pampel Games). | F43: Collection ↗ | G43: Asset Store ↗ | H43: 29.95 | I43: Yes | J43: MRM-32 blood spatter, paired with Gore Simulator. Vendor code in _Project/Code/Vendor. | L43: Docs ↗ | M43: Blood Factory v1.3 | N43: No | O43: Owned | Q43: Pampel Games | R43: 1.4 | S43: 2026-06-28
B44: AST-041 | C44: Blaze AI Engine | D44: AI & Behavior | E44: Universal enemy/companion AI: patrol, chase, cover-shooting, hit states on NavMesh. | F44: Collection ↗ | G44: Asset Store ↗ | H44: 40 | I44: Yes | J44: MRM-34 Spotter AI and the shared enemy framework (MRM-27 onward). Verified live. | M44: Blaze AI Engine v3.4.21 (20 May 2026) | N44: No | O44: Owned | Q44: Pathiral | R44: 3.4.22 | S44: 2026-06-22
B45: AST-042 | C45: A* Pathfinding Project Pro | D45: AI & Behavior | E45: Fast, flexible pathfinding (grid, navmesh, recast) for large worlds. | F45: Collection ↗ | G45: Asset Store ↗ | H45: 140 | I45: No | J45: Dropped in Round 2 in favour of Blaze AI (NavMesh). Keep for other projects. | L45: Docs ↗ | M45: A Pathfinding Project Pro v5.4.6 | N45: No | O45: Owned | Q45: Aron Granberg | R45: 5.4.7 | S45: 2026-08-29
B46: AST-043 | C46: Northern Lights Pack | D46: Sky & Atmosphere | E46: Collection of aurora borealis particle effects. | F46: Collection ↗ | G46: Asset Store ↗ | H46: 15 | I46: Yes | J46: Installed — northern lights in the Alaskan night sky (MRM-47). | M46: Northern Lights Pack v1.1.1 | N46: Yes | O46: Owned | Q46: Ian Scilipoti | R46: 1.1.1 | S46: 2021-01-21
B47: AST-044 | C47: ULTIMATE ANIMATION COLLECTION | D47: Animation — Clips & Mocap | E47: Huge human mocap library for Mecanim Humanoid (3,000+ clips). | F47: Collection ↗ | G47: Asset Store ↗ | H47: 259.99 | I47: Yes | J47: Installed — enemy locomotion/combat clips (MRM-31 / 29 / 35 / 37). ⚠ Import selectively. | M47: ULTIMATE ANIMATION COLLECTION v1.65 | N47: Yes | O47: Owned | Q47: PROTOFACTOR, INC | R47: 1.65 | S47: 2026-08-16
B48: AST-045 | C48: Blood VFX Essentials | D48: VFX — Blood & Gore | E48: Cinematic blood splashes plus magic and ambient flipbook effects. | F48: Collection ↗ | G48: Asset Store ↗ | H48: 60 | I48: No | J48: Marked 'NO USE' by you. | M48: NO USE - Blood VFX Essentials v1.0 | N48: Yes | O48: Owned | Q48: Piloto Studio | R48: 1.0 | S48: 2026-05-29
B49: AST-046 | C49: HQ FPS Weapons 2.0 | D49: FPS Frameworks & Templates | E49: Fully animated modern FPS weapons, arms and items, plus the FPSCore controller (PolymindGames). | F49: Collection ↗ | G49: Asset Store ↗ | H49: 49.99 | I49: Yes | J49: MRM-9 player controller (FPSCore) and MRM-22 / 24 / 25 weapons and arms — all 19 weapons share one FP_Arms skeleton. | M49: HQ FPS Weapons 2.0 v2.0.3 (30 May 2025) | N49: Yes | O49: Owned | Q49: Polymind Games | R49: 2.0.3 | S49: 2025-05-29
B50: AST-047 | C50: TopDown Nature Library 1000+ | D50: Vegetation & Nature | E50: 1,200+ top-down nature and botanical props. | F50: Collection ↗ | G50: Asset Store ↗ | H50: 24.99 | I50: Yes | J50: MRM-70 island vegetation (Art/Environment/Vegetation/TopDownNature). | M50: TopDown Nature Library 1000 v1.0 | N50: Yes | O50: Owned | Q50: Apex Geometry | R50: 1.0 | S50: 2026-04-16
B51: AST-048 | C51: Wendigo - Forest Beast Collection | D51: Characters — Horror & Creatures | E51: Rigged wendigo horror creature designed for jump scares. | F51: Collection ↗ | G51: Asset Store ↗ | H51: 39.99 | I51: No | J51: MRM-36 boss model (the Furman). Staged in Playground, not migrated yet. | M51: Wendigo - Forest Beast Collection v1.0 | N51: Yes | O51: Owned | Q51: GACHKOVSKYY | R51: 1.0 | S51: 2025-09-01
B52: AST-049 | C52: Gaia Pro VS - Terrain, Trees, Grass & Water for Unity 6 | D52: Terrain & World Building | E52: Terrain creation suite: stamping, erosion, biome spawners for trees, grass and water. | F52: Collection ↗ | G52: Asset Store ↗ | H52: 199 | I52: Yes | J52: MRM-70 — editor-time terrain shaping and the 9 biome spawners. Runtime/water/lighting parts deliberately not imported. | M52: Gaia Pro VS - Terrain Trees Grass Water for Unity 6 v4.2.4 | N52: No | O52: Owned | Q52: Procedural Worlds Inc | R52: 4.2.5 | S52: 2026-06-25
B53: AST-050 | C53: Crest Water 5 (Oceans, Rivers, Lakes) | D53: Water | E53: Class-leading ocean, river and lake water system for URP/HDRP/BIRP. | F53: Collection ↗ | G53: Asset Store ↗ | H53: 240 | I53: Yes | J53: MRM-71 sea and water bodies (embedded package), plus planar reflections for MRM-18. | L53: Docs ↗ | M53: Crest Water 5 (Oceans Rivers Lakes) v5.9.2 | N53: No | O53: Owned | Q53: Wave Harmonic | R53: 5.10.1 | S53: 2026-08-29
B54: AST-051 | C54: Log Cabin | D54: Environments & Level Kits | E54: Fully furnished forest log cabin. | F54: Collection ↗ | G54: Asset Store ↗ | H54: 39 | I54: No | J54: Playground only. Cabin staging candidate for the island. | M54: Log Cabin v1.5 | N54: Yes | O54: Owned | Q54: Gabro Media | R54: 1.5 | S54: 2026-02-09
B55: AST-052 | C55: URP - Wet Shaders : Flood and Rainy Puddles | D55: Shaders & Post-Processing | E55: Wet surfaces, floods and rainy puddle shaders for URP. | F55: Collection ↗ | G55: Asset Store ↗ | H55: 12.49 | I55: No | J55: Adopted for MRM-18 main-menu staging. | K55: [Claude] Fixed: the original Asset Store link pointed to Log Cabin. | M55: URP - Wet Shaders Flood and Rainy Puddles v2022.3 | N55: No | O55: Owned | Q55: Ciconia Studio | R55: 2026.0.2 | S55: 2026-08-18
B56: AST-053 | C56: Altos - Volumetric Clouds, Skybox, and Weather for Unity URP | D56: Sky & Atmosphere | E56: Volumetric clouds, dynamic skybox, day/night and weather for URP. | F56: Collection ↗ | G56: Asset Store ↗ | H56: 45 | I56: No | J56: Rejected for the island (collides with AllSky + TimeManager); still an option for the main menu (R2.2). | M56: Altos - Volumetric Clouds Skybox and Weather for Unity URP v7.18.0 | N56: Yes | O56: Owned | Q56: OccaSoftware | R56: 7.18.0 | S56: 2026-08-17
B57: AST-054 | C57: Skybox Blender | D57: Sky & Atmosphere | E57: Smooth blending between skyboxes (e.g. for day/night). | F57: Collection ↗ | G57: Asset Store ↗ | H57: 9.99 | I57: No | J57: Parked — MRM-47 chose instant, story-hidden skybox swaps. | M57: Skybox Blender v2.2.3 (02 Jun 2025) | N57: Yes | O57: Owned | Q57: Pathiral | R57: 2.2.3 | S57: 2025-06-01
B58: AST-055 | C58: Highlight Plus 2 - All in One Outline & Selection Effects | D58: Shaders & Post-Processing | E58: Outline, glow, overlay, see-through and selection effects for 3D objects (Kronnect). | F58: Collection ↗ | G58: Asset Store ↗ | H58: 49.99 | I58: No | J58: Not installed. Its punk-outline look was rebuilt as a uGUI shader for menu buttons (MRM-18); the real component is still the plan for 3D interaction highlights (MRM-16 / MRM-42). | L58: Docs ↗ | M58: Highlight Plus 2 - All in One Outline Selection Effects v34.1 | N58: No | O58: Owned | Q58: Kronnect | R58: 34.4.1 | S58: 2026-09-05
B59: AST-056 | C59: Underground - Modular Abandoned Basement & Bunker Environment URP | D59: Environments & Level Kits | E59: Modular abandoned basement and bunker environment for URP. | F59: Collection ↗ | G59: Asset Store ↗ | H59: 49.99 | I59: No | J59: Candidate for mine / bunker interiors. | M59: Underground - Modular Abandoned Basement Bunker Environment URP v1.0 (23 May 2025) | N59: Yes | O59: Owned | Q59: Ilumisoft | R59: 1.0 | S59: 2025-05-23
B60: AST-057 | C60: Screenspace VFX | D60: VFX — Particles | E60: Stylized screen-space status-effect overlays (buffs, debuffs, mind states). | F60: Collection ↗ | G60: Asset Store ↗ | H60: 29.99 | I60: No | J60: Candidate for status overlays (poison, fear, drugs — MRM-53 / MRM-55). | M60: Screenspace VFX v1.1 | N60: Yes | O60: Owned | Q60: Piloto Studio | R60: 1.1 | S60: 2026-05-22
B61: AST-058 | C61: Survival Horror Game Music Pack | D61: Audio — Music | E61: Cinematic survival-horror music collection (Dave Deville). | F61: Collection ↗ | G61: Asset Store ↗ | H61: 24.99 | I61: No | J61: Marked 'NO USE' by you. | K61: [Claude] Fixed: the original Asset Store link pointed to Screenspace VFX. | M61: NO USE Survival Horror Game Music Pack v1.0 | N61: Yes | O61: Owned | Q61: Dave Deville | R61: 1.0 | S61: 2019-11-19
B62: AST-059 | C62: Fluid Seamless Portals - Full | D62: Environments & Level Kits | E62: Seamless drag-and-drop portals for perfect teleportation. | F62: Collection ↗ | G62: Asset Store ↗ | H62: 58 | I62: No | J62: Transitions between special locations such as the mine. | K62: Will be useful for the transitions between special locations like the mine | L62: Docs ↗ | M62: Fluid Seamless Portals - Full v2.0 | N62: Yes | O62: Owned | Q62: Damian Gonzalez | R62: 2.0 | S62: 2024-02-01
B63: AST-060 | C63: Poly Universal Pack | D63: Props & Weapons | E63: Massive stylized pack with 7,000+ handmade models. | F63: Collection ↗ | G63: Asset Store ↗ | H63: 450 | I63: No | J63: Staging props for any location. | K63: A lot of very useful props that can be useful for staging in any location REVIEWED 2026-10-03 and REJECTED for Mr. Moonlight (useful in general, not for this game). Deleted from Playground to save disk; AST-060.zip kept in 01_DOWNLOAD. | M63: Poly Universal Pack v4.5 (15 Jul 2025) | N63: No | O63: Owned | Q63: polyperfect | R63: 5.3 | S63: 2026-09-14
B64: AST-061 | C64: Human Mega Animations Pack | D64: Animation — Clips & Mocap | E64: All of Kevin Iglesias' human animations in one pack. | F64: Collection ↗ | G64: Asset Store ↗ | H64: 130 | I64: No | J64: Extra humanoid clips for NPCs and enemies. | K64: A lot of useful animations | M64: Human Mega Animations Pack v2.0 (06 May 2026) | N64: Yes | O64: Owned | Q64: Kevin Iglesias | R64: 2.0 | S64: 2026-05-06
B65: AST-062 | C65: Forest animals 2.0 | D65: Characters — Animals | E65: 77 variations of 8 wild animal types, fully animated. | F65: Collection ↗ | G65: Asset Store ↗ | H65: 200 | I65: No | J65: Island wildlife (deer, bears, etc.). The wolf is covered by another asset. | K65: A lot of animals that can be useful for integrating them into the game there is also a wolf but the wolf will be covered with another asset. | M65: Forest animals 2.0 v1.1 | N65: Yes | O65: Owned | Q65: Red Deer | R65: 1.1 | S65: 2023-11-11
B66: AST-063 | C66: Dissolve FX: Master Kit | D66: Shaders & Post-Processing | E66: 28 VFX Graph dissolve, materialize and morph effects. | F66: Collection ↗ | G66: Asset Store ↗ | H66: 45 | I66: No | J66: Enemy death/spawn dissolves and Legion mode. | K66: Will be used for the center grading enemies and the Legion mode [Claude] 2026-10-01: staged in Playground (PLAYGROUND/AST-063). Added the Visual Effect Graph 17.3.0 package to Playground for its VFX scripts; local fly-cam helper for the demo scenes. 4 Standard materials + 1 Autodesk Interactive converted to URP/Lit. Not moved to Mr. Moonlight (its Burn Dissolve look is already ported into RetroLit, MRM-85). | L66: Docs ↗ | M66: Dissolve FX Master Kit v2.2 | N66: Yes | O66: Owned | Q66: INab Studio | R66: 2.2 | S66: 2026-08-04
B67: AST-064 | C67: Blood Stylized VFX Starter Kit | D67: VFX — Blood & Gore | E67: Stylized elemental VFX: explosions, projectiles, auras, beams. | F67: Collection ↗ | G67: Asset Store ↗ | H67: 39.99 | I67: No | J67: Enemy special attacks, especially Legion mode. | K67: Useful for some special attacks of some enemies, especially on Legion mode | M67: Blood Stylized VFX Starter Kit v1.1 | N67: Yes | O67: Owned | Q67: Piloto Studio | R67: 1.1 | S67: 2026-05-24
B68: AST-065 | C68: Chains VFX | D68: VFX — Particles | E68: Dark-fantasy chains, portals and corrupted-energy VFX. | F68: Collection ↗ | G68: Asset Store ↗ | H68: 29.99 | I68: No | J68: Enemy special attacks, especially Legion mode. | K68: Useful for some special attacks of some enemies, especially on Legion mode | M68: Chains VFX v1.0 | N68: Yes | O68: Owned | Q68: Piloto Studio | R68: 1.0 | S68: 2026-04-06
B69: AST-066 | C69: URP Complete VFX Bundle | D69: VFX — Particles | E69: 500+ curated URP VFX bundle. | F69: Collection ↗ | G69: Asset Store ↗ | H69: 297.99 | I69: No | J69: General VFX library, especially for Legion mode. | K69: A lot of visual effects that can be useful for the game, especially Legion mode [Claude] Store renumbered its versions (now 1.0.2026.3, Aug 2026); yours is older. | M69: URP Complete VFX Bundle v1.0.25 | N69: No | O69: Owned | Q69: Vefects | R69: 1.0.2026.3 | S69: 2026-08-07
B70: AST-067 | C70: Anime Girls Pack | D70: Characters — Anime | E70: Bundle of anime girl characters (SURIYUN). | F70: Collection ↗ | G70: Asset Store ↗ | H70: 580 | I70: No | J70: Personal library — not for Mr. Moonlight. | M70: Anime Girls Pack v3.2 | N70: Yes | O70: Owned | Q70: SURIYUN | R70: 3.2 | S70: 2025-12-15
B71: AST-068 | C71: Super Level Optimizer 2 | D71: Optimization & Performance | E71: Level optimizer: mesh combining, atlasing and LOD generation. | F71: Collection ↗ | G71: Asset Store ↗ | H71: 69.95 | I71: No | J71: Optimization candidate for the island (draw calls). | K71: Can be useful for optimizing the game | M71: Super Level Optimizer 2 v1.0.5 | N71: Yes | O71: Owned | Q71: New Game Studio | R71: 1.0.5 | S71: 2026-09-03
B72: AST-069 | C72: Stealth Finishers - Knife and Hand | D72: Animation — Clips & Mocap | E72: Knife/hand stealth finishers, cover movement and body carry/drag. | F72: Collection ↗ | G72: Asset Store ↗ | H72: 39.99 | I72: No | J72: Melee enemy attacks and takedowns. | K72: Contains some animations that can be used for melee enemies. | M72: Stealth Finishers - Knife and Hand v1.0 | N72: Yes | O72: Owned | Q72: RamsterZ | R72: 1.0 | S72: 2022-07-04
B73: AST-070 | C73: Old Wooden church | D73: Environments & Level Kits | E73: Single low-poly old wooden church model (diffuse + normal). | G73: Asset Store ↗ | H73: 9.99 | I73: Yes | J73: MRM-72 (first static prop through the wizard) · Base for the demo's church. | K73: This will be our base for the church use on the demo. [Claude] 2026-10-01: church built in Mr. Moonlight: Art/Environment/WoodenChurch (FBX re-exported through Blender, 9 RetroLit materials, albedos pixelated at 512) + Prefabs/World/Prop_WoodenChurch.prefab. Awaiting Carlos's review sign-off. Also staged in Playground (PLAYGROUND/AST-070, 11 Standard materials converted, ground material + 4 missing wood albedos wired). | M73: Assume the last version. | N73: Yes | O73: Owned | Q73: Aleksn09 | R73: 1.0 | S73: 2020-04-09
B74: AST-071 | C74: Mining Tunnel - Map Series 2 - | D74: Environments & Level Kits | E74: Modular mining-tunnel map parts. | G74: Asset Store ↗ | H74: 67.99 | I74: No | J74: Main staging for the demo's mine. | K74: Will we use it for the main staging on the demo | M74: Assume the last version. | N74: Yes | O74: Owned | Q74: CatStudio | R74: 2.0.0 | S74: 2026-02-26
B75: AST-072 | C75: Japanese Dungeons | D75: Environments & Level Kits | E75: Japanese-style modular dungeon kit. | G75: Asset Store ↗ | H75: 20 | I75: No | J75: Main staging on the demo. | K75: Will we use it for the main staging on the demo | M75: Assume the last version. | N75: Yes | O75: Owned | Q75: Edo Factory | R75: 1.2.0 | S75: 2026-01-19
B76: AST-073 | C76: Campsite - Retro Style Modular Environment Pack | D76: Environments & Level Kits | E76: Retro-style (low-res textures) modular campsite pack. | G76: Asset Store ↗ | H76: 19.99 | I76: No | J76: Campsite staging — the retro texture style suits the PSX look. | K76: Useful for the campsite | M76: Assume the last version. | N76: Yes | O76: Owned | Q76: Revolving Pizza Games | R76: 1.0 | S76: 2026-07-30
B77: AST-074 | C77: Graveyard Tombstones | D77: Environments & Level Kits | E77: Stylized graveyard tombstones set. | G77: Asset Store ↗ | H77: 15.99 | I77: Yes | J77: Church graveyard staging. | K77: Useful for the Church staging [Claude] 2026-10-01: staged in Playground (PLAYGROUND/AST-074); its Packages/manifest.json was skipped. Clean, no input or material fixes needed. Pending move to Mr. Moonlight. [Claude] 2026-10-09: all 63 prefabs moved into Mr. Moonlight: Art/Buildings & Props/AST-074 (Graveyard Tombstones)/{Prefabs,Meshes,Materials,Textures}. 9 RetroLit materials, BaseColor pixelated at 512 (normals 256), vendor GUIDs kept, vendor colliders untouched (collider policy not run). Not placed in a scene, not reviewed. Playground copy still staged. | M77: Assume the last version. | N77: Yes | O77: Owned | Q77: Lyrebird Studio | R77: 2.0 | S77: 2024-10-31
B78: AST-075 | C78: Retro Action - 16-bit style Rock & Metal Combat Music Pack | D78: Audio — Music | E78: 16-bit style rock and metal combat music with loops. | G78: Asset Store ↗ | H78: 59.99 | I78: No | J78: Legion mode music. | K78: Music useful for the Legion mode | M78: Assume the last version. | N78: Yes | O78: Owned | Q78: Rodrigo Flores Music | R78: 1.0 | S78: 2026-08-12
B79: AST-076 | C79: Heavy Action Music Pack – Driving Metal & Combat Themes | D79: Audio — Music | E79: Driving metal and combat themes with seamless loops. | G79: Asset Store ↗ | H79: 29.99 | I79: No | J79: Legion mode music. | K79: Music useful for the Legion mode [Claude] 2026-10-01: staged in Playground (PLAYGROUND/AST-076), 60 audio clips, no scene. Pending move to Mr. Moonlight. | M79: Assume the last version. | N79: Yes | O79: Owned | Q79: Rodrigo Flores Music | R79: 1.0.2 | S79: 2026-06-17
B80: AST-077 | C80: PSX Flashlight / Lantern Pack 6 of 6 | D80: Props & Weapons | E80: PSX-style flashlight/lantern low-poly pack (6 of 6). | G80: itch.io ↗ | H80: Pay what you want | I80: Yes | J80: The old-timer's lamp (Art/Props/Lamp). | K80: I used the lamp that the old timer uses from this asset. [Claude] Moved to the owned section — already in the project. | M80: Pay what you want download | N80: Yes | O80: Owned | Q80: Retro Assets Library (itch.io)
B81: AST-116 | C81: Technie Collider Creator 2 | D81: Physics & Simulation | E81: Automatic and hand-crafted accurate colliders for rigid and skinned meshes. | F81: Collection ↗ | G81: Asset Store ↗ | H81: 70 | I81: Yes | J81: MRM-84: Better, cheaper tree colliders on the island (~5,900 vegetation colliders today). In use: its paint brush marks which triangles are wood; the collider is built by WoodColliderTool. | K81: Intended to optimize and improve the colliders of the trees on the island [Claude] 2026-09-21: installed in Mr. Moonlight at Assets/Technie/PhysicsCreator and used for the MRM-84 tree colliders (moved out of the "not yet in project" section). | M81: Technie Collider Creator 2 v1.3.1 | N81: Yes | O81: Owned | P81: Owned (was P1 · #16) | Q81: Triangular Pixels | R81: 1.3.1 | S81: 2026-07-24
B82: OWNED / IN PROJECT — missing from the original list (yellow = review these)
B83: AST-078 | C83: HAZE - Volumetric Fog & Lighting for URP | D83: Sky & Atmosphere | E83: Artist-friendly volumetric fog and lighting for URP. | G83: Asset Store ↗ | H83: 35 | I83: Yes | J83: Island fog (renderer feature on PC_Renderer). Only renders when the Main Camera has post-processing on. | K83: [Claude] Added — found in the project / project docs, was not on the list. | L83: Docs ↗ | M83: Installed — version not recorded | N83: Unknown | O83: Owned | Q83: Harry Alisavakis | R83: 1.2.5 | S83: 2026-08-06
B84: AST-079 | C84: Retro Shaders Pro for URP | D84: Shaders & Post-Processing | E84: PSX/N64-style shaders and CRT post effects: vertex snapping, affine textures, pixelation. | G84: Asset Store ↗ | H84: 15.99 | I84: Yes | J84: The whole PSX look: RetroLit material shader + CRT post (PC_Renderer). | K84: [Claude] Added — found in the project / project docs, was not on the list. | M84: Installed — version not recorded | N84: Unknown | O84: Owned | Q84: Daniel Ilett | R84: 1.5.6 | S84: 2026-06-19
B85: AST-080 | C85: Flora | D85: Optimization & Performance | E85: BatchRendererGroup instanced renderer for terrain foliage and prefab instances. | G85: Asset Store ↗ | H85: 60 | I85: Yes | J85: Renders the island vegetation (MRM-70). Embedded package. ⚠ Phantom-tree rendering bug open. | K85: [Claude] Added — found in the project / project docs, was not on the list. | L85: Docs ↗ | M85: Installed v6.3.35 (embedded package) | N85: No | O85: Owned | Q85: Magnetic Arcade | R85: 6.4.4 | S85: 2026-09-13
B86: AST-081 | C86: Text Animator for Unity | UI Toolkit and Text Mesh Pro | D86: UI & HUD | E86: Typewriter and animated text effects for TextMesh Pro and UI Toolkit. | G86: Asset Store ↗ | H86: 65 | I86: Yes | J86: Animated menu/HUD text (MRM-18 punk-zine UI). | K86: [Claude] Added — found in the project / project docs, was not on the list. | L86: Docs ↗ | M86: Installed v3.14.2 (embedded package) | N86: No | O86: Owned | Q86: Febucci | R86: 3.20.1 | S86: 2026-09-16
B87: AST-082 | C87: DOTween Pro | D87: Animation & Rigging Tools | E87: Tweening engine: move, fade, shake, paths and sequences, with visual editors. | G87: Asset Store ↗ | H87: 15 | I87: Yes | J87: Project standard for smooth transitions (menu title reveal, UI fades). | K87: [Claude] Added — found in the project / project docs, was not on the list. | L87: Docs ↗ | M87: Installed — version not recorded | N87: Unknown | O87: Owned | Q87: Demigiant | R87: 1.0.430 | S87: 2026-06-23
B88: AST-083 | C88: Simple Water Shader URP | D88: Water | E88: Lightweight free water shader with a few look controls. | G88: Asset Store ↗ | H88: 0 | I88: Yes | J88: Still installed, but Crest replaced it on the sea (MRM-71) — removal candidate. | K88: [Claude] Added — found in the project / project docs, was not on the list. | M88: Installed v1.0.0 | N88: Yes | O88: Owned | Q88: IgniteCoders | R88: 1.0.0 | S88: 2021-03-19
B89: AST-084 | C89: Terrain Asset Pack | Terrain Sample | D89: Terrain & World Building | E89: Unity's official terrain layers, brushes and sample vegetation. | G89: Asset Store ↗ | H89: 0 | I89: Yes | J89: MRM-70 vegetation prefabs reference its meshes (fragile — copy what ships). ~1.9 GB download. | K89: [Claude] Added — found in the project / project docs, was not on the list. | L89: Docs ↗ | M89: Installed — version not recorded | N89: Unknown | O89: Owned | Q89: Unity Technologies | R89: 2.0.1 | S89: 2022-07-28
B90: AST-085 | C90: Burntwax FPS Engine | D90: FPS Frameworks & Templates | E90: Free modular FPS foundation: movement, camera, weapons, save/load, state machine. | G90: Asset Store ↗ | H90: 0 | I90: Yes | J90: Legacy: the first player controller (MRM-9), replaced by HQ FPS Weapons' FPSCore. Still in ThirdParty + Vendor code — removal candidate. | K90: [Claude] Added — found in the project / project docs, was not on the list. | M90: Installed — version not recorded | N90: Unknown | O90: Owned | Q90: Burntwax Collective | R90: 1.0.2 | S90: 2026-07-13
B91: AST-086 | C91: AllSky - 220+ Sky / Skybox Set | D91: Sky & Atmosphere | E91: 220+ skyboxes: day, night, fantasy, space, overcast. | G91: Asset Store ↗ | H91: 20 | I91: Yes | J91: Island skyboxes (MRM-47) — 6 extracted, 4 ship. | K91: [Claude] Added — found in the project / project docs, was not on the list. | L91: Docs ↗ | M91: Extracted from cache — version not recorded | N91: Unknown | O91: Owned | Q91: rpgwhitelock | R91: 5.2.0 | S91: 2024-07-20
B92: AST-087 | C92: RETRO REALISM: Lonely Forest | D92: Vegetation & Nature | E92: PS1-style forest pack: trees, boulders, logs, stumps, bushes, ferns. | G92: itch.io ↗ | H92: 14.99 | I92: Yes | J92: Main source art for island trees and rocks (MRM-70). | K92: [Claude] Added — found in the project / project docs, was not on the list. | M92: Source art at E:\Props\Environment | N92: Unknown | O92: Owned | Q92: Matt Reeves Dev (itch.io)
B93: AST-088 | C93: Grass Flowers Pack Free | D93: Vegetation & Nature | E93: 12 grass and flower billboard textures (ALP). | G93: Asset Store ↗ | H93: 0 | I93: Yes | J93: Grass/flower detail textures (Vegetation/GrassFlowers). | K93: [Claude] Added — found in the project / project docs, was not on the list. | M93: Source art | N93: Unknown | O93: Owned | Q93: Objective Environment | R93: 1.1 | S93: 2026-01-21
B94: AST-089 | C94: Terrain Textures Pack Free | D94: Textures & Materials | E94: 5 tileable terrain ground textures (ALP). | G94: Asset Store ↗ | H94: 0 | I94: Yes | J94: Island ground textures. | K94: [Claude] Added — found in the project / project docs, was not on the list. | M94: Source art | N94: Unknown | O94: Owned | Q94: Objective Environment | R94: 1.0 | S94: 2019-02-14
B95: AST-090 | C95: Yughues Free Ground Materials | D95: Textures & Materials | E95: 30 ground and soil materials: moss, clay, snow, gravel. | G95: Asset Store ↗ | H95: 0 | I95: Yes | J95: Island ground textures. | K95: [Claude] Added — found in the project / project docs, was not on the list. | M95: Source art | N95: Unknown | O95: Owned | Q95: Nobiax / Yughues | R95: 1.1 | S95: 2025-04-03
B96: AST-091 | C96: MCP for Unity (CoplayDev) | D96: Editor Tools & Utilities | E96: Model Context Protocol bridge that lets Claude read and edit the Unity Editor. | G96: GitHub ↗ | H96: 0 | I96: Yes | J96: Editor bridge used by Claude Code for scene/inspector work (UPM git package). | K96: [Claude] Added — found in the project / project docs, was not on the list. | M96: Installed from git (main branch) | N96: Unknown | O96: Owned | Q96: CoplayDev (GitHub)
B97: AST-092 | C97: Vegetation Spawner | FREE - Automatic Tree/Grass Placement | D97: Terrain & World Building | E97: Procedural rule-based tree and grass spawner for Unity terrain (Staggart). | G97: Asset Store ↗ | H97: 0 | I97: No | J97: Used early in MRM-70, now replaced by Gaia biome spawners. | K97: [Claude] Added — found in the project / project docs, was not on the list. | M97: Owned (per project docs) | N97: Unknown | O97: Owned | Q97: Staggart Creations | R97: 1.1.0 | S97: 2024-11-27
B98: AST-093 | C98: Drunk Color Pulse (Post-Processing Effect) | D98: Shaders & Post-Processing | E98: Dizzy/drunk full-screen effect with a pulsing colour overlay. | G98: Asset Store ↗ | H98: 0 | I98: No | J98: Adopted for MRM-55 — drunk effect (staged in Playground). | K98: [Claude] Added — found in the project / project docs, was not on the list. | M98: Owned (per project docs) | N98: Unknown | O98: Owned | Q98: Synaptic Response | R98: 1.0.0 | S98: 2025-12-08
B99: AST-094 | C99: Sewer/Underground Modular Pack v4.0 | D99: Environments & Level Kits | E99: Modular sewer and underground transition level kit. | G99: Asset Store ↗ | H99: 30 | I99: No | J99: Adopted for MRM-60 mine interiors (staged in Playground). | K99: [Claude] Added — found in the project / project docs, was not on the list. | M99: Owned (per project docs) | N99: Unknown | O99: Owned | Q99: Wenvio | R99: 4.2 | S99: 2024-12-17
B100: AST-095 | C100: Underground Atmospheres Sound Effects Pack 2021 | D100: Audio — SFX & Ambience | E100: Underground ambiences: tunnels, sewers, caves, ice caverns. | G100: Asset Store ↗ | H100: 29.99 | I100: No | J100: Adopted for MRM-38 mine sound layers. | K100: [Claude] Added — found in the project / project docs, was not on the list. | L100: Docs ↗ | M100: Owned (per project docs) | N100: Unknown | O100: Owned | Q100: Olivier Girardot | R100: 2.0 | S100: 2021-05-24
...

Sheet Legend
B2: How to read the index
B3: ID (AST-###) | C3: Permanent identifier. Numbers were assigned once, in this file's order; they never change if you sort, filter or add rows. New assets get the next free number.
B4: Yellow row | C4: Owned or already used in Mr. Moonlight, but missing from your original list.
B5: Price in green | C5: The asset has a collection URL.
B6: Price in red | C6: No collection URL — the store/source is the only place to get it.
B7: Price | C7: Full (non-sale) price in USD. 'Free' = $0. itch.io 'Pay what you want' and unreadable pages are written as text.
B8: in Mr Moonlight? = Yes (green) | C8: Actually installed or used in the Mr. Moonlight project today (checked against the project folders and docs), not just planned. The ticket is at the start of the purpose column.
B9: up to date? = No (orange) | C9: The Asset Store has a newer version than your downloaded file. 'Unknown' = the version isn't recorded. Store versions read on 2026-09-16.
B10: status / priority | C10: Owned rows have no priority. The wishlist is sorted by priority; #1 is the first thing to get.
B12: Priority tiers
B13: P1 · Get first — Mr. Moonlight demo | C13: 13 assets · ~$133.41 at full price · Direct value for the demo now: enemy AI/senses, horror enemies and animations, gore, flashlight, UI sound, free packs.
B14: P2 · Mr. Moonlight — October / later | C14: 5 assets · ~$138.95 at full price · Useful for Mr. Moonlight but not urgent: cutscenes, optimization, destructible trees, swimming, boats.
B15: P3 · General toolkit — other projects | C15: 15 assets · ~$817.96 at full price · Strong general tools for future projects: procedural generation, anti-cheat, networking, IK/physics.
B16: P4 · Niche templates & packs | C16: 4 assets · ~$218.97 at full price · Genre templates and niche packs, kept for reference.
B17: P5 · Personal library — anime / gooner | C17: 11 assets · ~$660.00 at full price · Personal library, not for Mr. Moonlight.
B19: Categories
B20: AI & Behavior | C20: 8 assets
B21: Animation & Rigging Tools | C21: 14 assets
B22: Animation — Clips & Mocap | C22: 25 assets
B23: Audio Tools | C23: 2 assets
B24: Audio — Music | C24: 4 assets
B25: Audio — SFX & Ambience | C25: 13 assets
B26: Blender Add-ons | C26: 2 assets
B27: Characters — Animals | C27: 5 assets
B28: Characters — Anime | C28: 5 assets
B29: Characters — Gooner | C29: 24 assets
B30: Characters — Horror & Creatures | C30: 11 assets
B31: Characters — Humans & Stylized | C31: 9 assets
... B51: Water | C51: 8 assets
B53: Changes made while building this file
B54: Duplicates merged | C54: BloodOcean, Aoi Character Pack, Magica Cloth 2, Advanced Zombie AI, Weeper Horror Ghost Pack, Classic Female Ghost and Anime Girl Characters – Bikini were each listed twice. Merged into one row, notes combined.
B55: Wrong links fixed | C55: URP Wet Shaders pointed to Log Cabin · Survival Horror Game Music Pack pointed to Screenspace VFX · CombatGirls Pistol's collection link pointed to the Dual Pistol pack.
B56: Moved to owned | C56: PSX Flashlight / Lantern Pack 6 — its lamp is already in the project (Art/Props/Lamp).
B57: Not found on the Asset Store | C57: Alice Style Character, Anime Style Girl: Haruka, Anime Girl Characters – Bikini, Monster Sounds Pack, Guns Sound Essentials — probably delisted; only the collection links work.
B58: 2026-09-19 update | C58: 14 newly downloaded files. 11 were wishlist rows (AST-118 to 126, 144, 147): moved into the 'OWNED (FROM WISHLIST)' section, original ranks kept in the priority column. 3 were on no list and got new IDs: AST-264 SensorToolkit 2, AST-265 Emerald AI 2026, AST-266 Advanced Cable Creator (yellow rows). The wishlist tier totals above now count only what is still un-owned. This file moved from Desktop\assets to Documents\Asset Collection\03_documentation.
B59: 2026-09-19 update (2nd) | C59: 13 more downloaded files, every one already a wishlist row (AST-127, 128, 129, 131, 132, 134, 135, 137, 142, 143, 156, 157, 232): moved into the 'OWNED (FROM WISHLIST)' section, original ranks kept in the priority column. No new IDs. AST-143 Cineaster is marked 'No' for up to date (file v1.0.2, store 1.0.3). The tier totals above now count only what is still un-owned.
B60: 2026-09-21 update | C60: 13 more downloaded files, every one already a wishlist row (AST-130, 133, 139, 150, 151, 155, 162, 163, 164, 165, 166, 171, 173): moved into the 'OWNED (FROM WISHLIST)' section, original ranks kept in the priority column. No new IDs. Not installed in any project. Two are behind the store: AST-165 Crest Water 5 - Whirlpool (file 1.0.3, store 1.1.2) and AST-173 DunGen (file 2.18.14, store 2.19.13). AST-151 Monster Sounds Pack has no store version, so 'Unknown'. Tier totals recomputed.
B61: 2026-09-21 update (2nd) | C61: AST-116 Technie Collider Creator 2 moved from 'OWNED (FROM WISHLIST)' to 'OWNED — downloaded assets' and marked in Mr. Moonlight = Yes (installed at Assets/Technie/PhysicsCreator, used for MRM-84). AST-147 Asset Optimizer Pro and AST-164 Ether Skyboxes staged in the Playground project (noted in their notes column); AST-054 Skybox Blender was already there.
B62: 2026-09-25 update | C62: 9 more downloaded files. 7 were wishlist rows (AST-167, 168, 169, 170, 184, 205, 206): moved into the 'OWNED (FROM WISHLIST)' section, original ranks kept in the priority column. 2 were on no list and got new IDs (AST-267 Cutscene Engine, AST-268 Procedural Generation Grid (Beta)), yellow rows. Tier totals and category counts recomputed.
B63: 2026-09-29 update | C63: 20 more downloaded files. 9 were wishlist rows (AST-175, 176, 177, 183, 187, 189, 190, 194, 195): moved into the 'OWNED (FROM WISHLIST)' section, original ranks kept in the priority column. 11 were on no list and got new IDs AST-269 to AST-279 (Advanced Dissolve, Medieval Wells Props, Draw Debug Tools, Dynamic Water Physics 2, Essential Footsteps SFX, Exporter for Unreal to/for Unity, Magic Time, Sci-Fi Game Sound Effects, SmartBuilder, Survival Essentials Pack, Ultimate Sound FX Bundle), yellow rows. Behind the store: AST-175, 176, 177, 183, 190, 195. AST-279 has no store page (publisher, price and version unknown). Tier totals and category counts recomputed.
B64: 2026-09-29 update (2nd) | C64: 12 more downloaded files, every one already a wishlist row (AST-145, 146, 153, 160, 172, 182, 193, 228, 229, 237, 238, 248): moved into the 'OWNED (FROM WISHLIST)' section, original ranks kept in the priority column. No new IDs. Not installed in any project. Behind the store: AST-172 Character Animation System (file 2.1.2, store 2.4.1), AST-228 Toony Tiny WW1 Soldiers (1.0 vs 1.1), AST-237 Aoi Character Pack (1.11 vs 1.16), AST-238 Honoka Futaba Basic Set (1.17 vs 1.18). Tier totals recomputed.
B65: 2026-09-30 update | C65: 11 more downloaded files. 7 were wishlist rows (AST-174, 180, 181, 192, 196, 197, 250): moved into the 'OWNED (FROM WISHLIST)' section, original ranks kept in the priority column. 1 was a re-download of an owned asset (AST-113 Realistic Blood VFX, v3.0 to v4.0; old zip replaced). 3 were on no list and got new IDs (AST-280 Beautify 3, AST-281 Toolkit for Steamworks 2026, AST-282 Volumetric Fog & Mist 2), yellow rows. Behind the store: AST-174, 180, 181, 281. AST-250 has no store page (version Unknown). Tier totals and category counts recomputed.
... B76: Source file | C76: The original ASSETS.xlsx is untouched.
